Workbook

Sheet Risultati
B1: Ragione sociale | C1: Partita IVA | D1: Chiusura bilancio | E1: Modello di contabilità | F1: TOT. VAL. DELLA PRODUZIONE migl EUR | G1: Ricavi vendite e prestazioni migl EUR | H1: Var. rimanenze prodotti migl EUR | I1: Materie prime e consumo migl EUR | J1: Variazione materie migl EUR | K1: Servizi migl EUR | L1: Totale costi del personale migl EUR | M1: Oneri diversi di gestione migl EUR | N1: Godimento beni di terzi migl EUR | O1: TOT Ammortamenti e svalut. migl EUR | P1: Accantonamenti per rischi migl EUR | Q1: Altri accantonamenti migl EUR | R1: TOTALE PROVENTI E ONERI FINANZIARI migl EUR | S1: TOTALE RETTIFICHE ATT. FINANZ. migl EUR | T1: TOTALE PROVENTI/ONERI STRAORDINARI migl EUR | U1: Totale Imposte sul reddito correnti, differite e anticipate migl EUR | V1: UTILE/PERDITA DI ESERCIZIO migl EUR | W1: Dipendenti | X1: Trend Ricavi n-1 % EUR | Y1: Trend Ricavi a 3 anni % EUR | Z1: Trend Ricavi a 5 anni % EUR | AA1: Trend EBITDA a 5 anni % EUR | AB1: TOTALE ATTIVO migl EUR | AC1: Cred. vs Clienti entro migl EUR | AD1: Cred. vs Clienti oltre migl EUR | AE1: TOTALE RIMANENZE migl EUR | AF1: Immobilizzazioni materiali destinate alla vendita migl EUR | AG1: TOTALE PATRIMONIO NETTO migl EUR | AH1: Fornitori entro migl EUR | AI1: Fornitori oltre migl EUR | AJ1: DEBITI A BREVE migl EUR | AK1: Debiti Finanziari migl EUR | AL1: TOT. DISPON. LIQUIDE migl EUR | AM1: Attività finanziarie per la gestione accentrata della tesoreria migl EUR | AN1: ATECO 2007 codice | AO1: ATECO 2007 descrizione | AP1: CREDITI VERSO SOCI migl EUR | AQ1: TOTALE IMMOB. IMMATERIALI migl EUR | AR1: TOTALE IMMOB. MATERIALI migl EUR | AS1: TOTALE IMMOB. FINANZIARIE migl EUR | AT1: TOTALE CREDITI migl EUR | AU1: TOTALE ATTIVITA' FINANZIARIE migl EUR | AV1: TOTALE DEBITI migl EUR | AW1: RATEI E RISCONTI migl EUR | AX1: RATEI E RISCONTI migl EUR | AY1: EBITDA migl EUR n-4
A2: 1. | B2: ESSELUNGA SPA | C2: 04916380159 | D2: 45291 | E2: Dettagliato | F2: 9120646 | G2: 9038616 | H2: 0 | I2: 6285561 | J2: 0 | K2: 1015920 | L2: 1052480 | M2: 99536 | N2: 25090 | O2: 406552 | P2: 23291 | Q2: 0 | R2: -103005 | S2: 58071 | T2: 1031 | U2: 39284 | V2: 129029 | W2: 23967 | X2: 5.910202 | Y2: 7.1247441 | Z2: 14.224044 | AA2: -11.973027 | AB2: 7890573 | AC2: 263230 | AD2: 0 | AE2: 565651 | AF2: 0 | AG2: 2200792 | AH2: 1693049 | AI2: 0 | AJ2: 2359478 | AK2: 3192105 | AL2: 252746 | AM2: 32110 | AN2: 471100 | AO2: Commercio al dettaglio in esercizi non specializzati con prevalenza di prodotti alimentari e bevande | AP2: 0 | AQ2: 220145 | AR2: 5222483 | AS2: 1159374 | AT2: 402192 | AU2: 53307 | AV2: 5393411 | AW2: 177519 | AX2: 14675 | AY2: 702930
A3: 2. | B3: LIDL ITALIA S.R.L. | C3: 02275030233 | D3: 45351 | E3: Dettagliato | F3: 7230231 | G3: 7158326 | H3: 0 | I3: 5027140 | J3: 217103 | K3: 657621 | L3: 673251 | M3: 47150 | N3: 84069 | O3: 226867 | P3: 1872 | Q3: 262 | R3: -24069 | S3: 558 | T3: 0 | U3: 77452 | V3: 193932 | W3: 20814 | X3: 7.04756 | Y3: 21.644515 | Z3: 38.929638 | AA3: 37.408386 | AB3: 3812743 | AC3: 2774 | AD3: 0 | AE3: 455584 | AF3: 3894 | AG3: 1902923 | AH3: 958299 | AI3: 6259 | AJ3: 1432997 | AK3: 657261 | AL3: 72756 | AM3: 212878 | AN3: 469000 | AO3: Commercio all'ingrosso non specializzato | AP3: 0 | AQ3: 111652 | AR3: 2747980 | AS3: 8537 | AT3: 182206 | AU3: 212878 | AV3: 1799919 | AW3: 20614 | AX3: 17256 | AY3: 379717
A4: 3. | B4: A.I.A. - AGRICOLA ITALIANA ALIMENTARE - S.P.A. | C4: 00233470236 | D4: 45291 | E4: Dettagliato | F4: 4814669 | G4: 4712306 | H4: 440 | I4: 4090111 | J4: 5280 | K4: 442257 | L4: 57265 | M4: 13255 | N4: 5091 | O4: 94636 | P4: 0 | Q4: 0 | R4: -17934 | S4: 0 | T4: 0 | U4: 21355 | V4: 67486 | W4: 687 | X4: 11.802779 | Y4: 24.983947 | Z4: 36.766654 | AA4: 60.629406 | AB4: 1576836 | AC4: 397265 | AD4: 0 | AE4: 27726 | AF4: 0 | AG4: 475818 | AH4: 365804 | AI4: 0 | AJ4: 825229 | AK4: 615258 | AL4: 49282 | AM4: 0 | AN4: 463210 | AO4: Commercio all'ingrosso di carne fresca, congelata e surgelata | AP4: 0 | AQ4: 150 | AR4: 523919 | AS4: 275760 | AT4: 585927 | AU4: 111758 | AV4: 1068841 | AW4: 3702 | AX4: 2313 | AY4: 125388
A5: 4. | B5: PAC 2000 A SOCIETA' COOPERATIVA | C5: 00163040546 | D5: 45291 | E5: Dettagliato | F5: 4537962 | G5: 3939071 | H5: 0 | I5: 4036095 | J5: -9543 | K5: 337244 | L5: 40571 | M5: 13047 | N5: 31947 | O5: 35158 | P5: 1000 | Q5: 12712 | R5: 10320 | S5: 0 | T5: 0 | U5: 7868 | V5: 42184 | W5: 790 | X5: 9.467291 | Y5: 17.621953 | Z5: 63.940179 | AA5: 18.448107 | AB5: 1636025 | AC5: 277213 | AD5: 0 | AE5: 160043 | AF5: 0 | AG5: 784103 | AH5: 704677 | AI5: 0 | AJ5: 784557 | AK5: 48096 | AL5: 87591 | AM5: 77 | AN5: 463890 | AO5: Commercio all'ingrosso di altri prodotti alimentari | AP5: 3026 | AQ5: 37853 | AR5: 365022 | AS5: 386597 | AT5: 540065 | AU5: 50083 | AV5: 815565 | AW5: 4939 | AX5: 5745 | AY5: 63226
A6: 5. | B6: COOP ALLEANZA 3.0 SOCIETA' COOPERATIVA | C6: 03503411203 | D6: 45291 | E6: Dettagliato | F6: 4372943 | G6: 3895925 | H6: -20509 | I6: 3028993 | J6: -16617 | K6: 462223 | L6: 596887 | M6: 79107 | N6: 145796 | O6: 106806 | P6: 5655 | Q6: 5500 | R6: 93308 | S6: -16956 | T6: 0 | U6: 14932 | V6: 20013 | W6: 16244 | X6: 1.7454805 | Y6: -3.8114223 | Z6: 6.7572385 | AA6: -148.41824 | AB6: 6246398 | AC6: 217674 | AD6: 8934 | AE6: 489231 | AF6: 0 | AG6: 1586205 | AH6: 703634 | AI6: 145 | AJ6: 3427654 | AK6: 3587640 | AL6: 225861 | AM6: 35328 | AN6: 471120 | AO6: Supermercati | AP6: 0 | AQ6: 173036 | AR6: 1077666 | AS6: 2652270 | AT6: 338663 | AU6: 1273876 | AV6: 4475076 | AW6: 3580 | AX6: 15795 | AY6: -135071
A7: 6. | B7: GS SPA | C7: 12683790153 | D7: 45291 | E7: Dettagliato | F7: 4481915 | G7: 3836122 | H7: 0 | I7: 3279750 | J7: 9279 | K7: 512822 | L7: 484359 | M7: 23033 | N7: 201389 | O7: 83298 | P7: 501 | Q7: 0 | R7: -15793 | S7: 0 | T7: 0 | U7: 435 | V7: -128746 | W7: 9392 | X7: -0.19279142 | Y7: -1.2921669 | Z7: 10.353829 | AA7: 88.887452 | AB7: 1548298 | AC7: 131231 | AD7: 1153 | AE7: 366643 | AF7: 0 | AG7: 152359 | AH7: 747001 | AI7: 0 | AJ7: 1303331 | AK7: 13 | AL7: 37962 | AM7: 0 | AN7: 471100 | AO7: Commercio al dettaglio in esercizi non specializzati con prevalenza di prodotti alimentari e bevande | AP7: 0 | AQ7: 242393 | AR7: 103985 | AS7: 340820 | AT7: 418326 | AU7: 0 | AV7: 1309071 | AW7: 1409 | AX7: 38171 | AY7: -15469
A8: 7. | B8: MD S.P.A. | C8: 03185210618 | D8: 45291 | E8: Dettagliato | F8: 3688201 | G8: 3591475 | H8: 0 | I8: 2769990 | J8: 4494 | K8: 309641 | L8: 281347 | M8: 16163 | N8: 87258 | O8: 89695 | P8: 3332 | Q8: 0 | R8: -11047 | S8: 0 | T8: 0 | U8: 34984 | V8: 80249 | W8: 7823 | X8: 7.7535384 | Y8: 19.540189 | Z8: 44.543083 | AA8: 58.204473 | AB8: 1742231 | AC8: 127902 | AD8: 0 | AE8: 187440 | AF8: 0 | AG8: 580263 | AH8: 712285 | AI8: 0 | AJ8: 967290 | AK8: 321976 | AL8: 195835 | AM8: 0 | AN8: 471120 | AO8: Supermercati | AP8: 0 | AQ8: 377888 | AR8: 607643 | AS8: 186865 | AT8: 173715 | AU8: 0 | AV8: 1116038 | AW8: 8794 | AX8: 12845 | AY8: 136517
A9: 8. | B9: SPESA INTELLIGENTE S.P.A. | C9: 02416840235 | D9: 45291 | E9: Dettagliato | F9: 3181536 | G9: 3162613 | H9: 0 | I9: 2472185 | J9: 8250 | K9: 212848 | L9: 225039 | M9: 11545 | N9: 13125 | O9: 67213 | P9: 0 | Q9: 0 | R9: 2678 | S9: 0 | T9: 0 | U9: 45598 | V9: 128413 | W9: 5557 | X9: 11.617276 | Y9: 26.84426 | Z9: 47.69814 | AA9: 66.959461 | AB9: 1359065 | AC9: 60566 | AD9: 0 | AE9: 118661 | AF9: 0 | AG9: 824811 | AH9: 402095 | AI9: 0 | AJ9: 522944 | AK9: 10515 | AL9: 37692 | AM9: 1561 | AN9: 471100 | AO9: Commercio al dettaglio in esercizi non specializzati con prevalenza di prodotti alimentari e bevande | AP9: 0 | AQ9: 18418 | AR9: 1074920 | AS9: 858 | AT9: 105277 | AU9: 1561 | AV9: 522997 | AW9: 8111 | AX9: 1678 | AY9: 142876
A10: 9. | B10: UNICOOP FIRENZE SOCIETA' COOPERATIVA IN SIGLA UNICOOP FIRENZE SC | C10: 00407780485 | D10: 45291 | E10: Dettagliato | F10: 3130808 | G10: 3014665 | H10: 0 | I10: 2397666 | J10: 10511 | K10: 246066 | L10: 290560 | M10: 50019 | N10: 8481 | O10: 99612 | P10: 0 | Q10: 26954 | R10: 37422 | S10: -1420 | T10: 0 | U10: 11377 | V10: 25564 | W10: 8172 | X10: 11.1997 | Y10: 24.896167 | Z10: 26.468763 | AA10: -36.931897 | AB10: 3806693 | AC10: 89563 | AD10: 0 | AE10: 143722 | AF10: 20841 | AG10: 1780860 | AH10: 429863 | AI10: 0 | AJ10: 1784883 | AK10: 1401171 | AL10: 210389 | AM10: 5040 | AN10: 471120 | AO10: Supermercati | AP10: 0 | AQ10: 36851 | AR10: 1375389 | AS10: 1252493 | AT10: 241745 | AU10: 513026 | AV10: 1934073 | AW10: 964 | AX10: 12236 | AY10: 159434
A11: 10. | B11: CONAD NORD OVEST SOCIETA' COOPERATIVA | C11: 01977130473 | D11: 45291 | E11: Dettagliato | F11: 3361341 | G11: 2997446 | H11: 0 | I11: 3024044 | J11: 25080 | K11: 202421 | L11: 31138 | M11: 6359 | N11: 0 | O11: 25543 | P11: 0 | Q11: 0 | R11: 15910 | S11: 0 | T11: -448 | U11: 1315 | V11: 60903 | W11: 484 | X11: 7.7557885 | Y11: 15.880226 | Z11: 24.223553 | AA11: 36.192216 | AB11: 1932957 | AC11: 110623 | AD11: 3132 | AE11: 129504 | AF11: 0 | AG11: 922469 | AH11: 367207 | AI11: 0 | AJ11: 616647 | AK11: 505577 | AL11: 156745 | AM11: 0 | AN11: 463920 | AO11: Commercio all'ingrosso non specializzato di prodotti alimentari, bevande e tabacco | AP11: 0 | AQ11: 75454 | AR11: 117115 | AS11: 596019 | AT11: 644162 | AU11: 213958 | AV11: 977455 | AW11: 4802 | AX11: 0 | AY11: 53086
A12: 11. | B12: AGRICOLA TRE VALLI - SOCIETA' COOPERATIVA | C12: 02447620234 | D12: 45291 | E12: Dettagliato | F12: 2938830 | G12: 2912605 | H12: 10406 | I12: 2192596 | J12: -3417 | K12: 334610 | L12: 300149 | M12: 10453 | N12: 101593 | O12: 1875 | P12: 0 | Q12: 0 | R12: -758 | S12: 0 | T12: 0 | U12: 23 | V12: 191 | W12: 6553 | X12: 13.829881 | Y12: 21.306228 | Z12: 31.697986 | AA12: -31.006061 | AB12: 459487 | AC12: 163391 | AD12: 0 | AE12: 237989 | AF12: 0 | AG12: 23651 | AH12: 286045 | AI12: 0 | AJ12: 411046 | AK12: 44544 | AL12: 622 | AM12: 0 | AN12: 101200 | AO12: Produzione di carne di volatili e prodotti della loro macellazione (attività dei mattatoi) | AP12: 0 | AQ12: 84 | AR12: 11237 | AS12: 69 | AT12: 209214 | AU12: 0 | AV12: 411046 | AW12: 244 | AX12: 271 | AY12: 4125
A13: 12. | B13: MAXI DI S.R.L. | C13: 00542090238 | D13: 45291 | E13: Dettagliato | F13: 2731583 | G13: 2690365 | H13: 0 | I13: 2036704 | J13: -23468 | K13: 251200 | L13: 226369 | M13: 17801 | N13: 40000 | O13: 83683 | P13: 0 | Q13: 800 | R13: 1450 | S13: 0 | T13: 0 | U13: 25213 | V13: 74731 | W13: 6762 | X13: 8.9094903 | Y13: 12.712543 | Z13: 26.621083 | AA13: 45.118172 | AB13: 1357200 | AC13: 28711 | AD13: 727 | AE13: 292224 | AF13: 0 | AG13: 719062 | AH13: 320714 | AI13: 0 | AJ13: 444956 | AK13: 231308 | AL13: 123845 | AM13: 0 | AN13: 471120 | AO13: Supermercati | AP13: 0 | AQ13: 36444 | AR13: 771154 | AS13: 68729 | AT13: 58277 | AU13: 0 | AV13: 614979 | AW13: 8392 | AX13: 6528 | AY13: 125537
... A30: 30. | B30: UNILEVER ITALIA MKT. OPERATIONS SRL - FATTA PRECISAZIONE CHE DETT A DENOMINAZIONE POTRA' ESSERE SCRITTA CON O SENZA IL PUNTO DOPO LA PAROLA MKT. | C30: 06397510964 | D30: 45291 | E30: Dettagliato | F30: 1504405.3 | G30: 1491775.7 | H30: 0 | I30: 686433.15 | J30: 1992.151 | K30: 671147.94 | L30: 49687.472 | M30: 12288.572 | N30: 62809.812 | O30: 18927.732 | P30: 676 | Q30: 349.322 | R30: 12945.164 | S30: 0 | T30: 0 | U30: 3732.163 | V30: 9306.114 | W30: 413 | X30: 3.5954845 | Y30: 4.8985658 | Z30: 1.3989368 | AA30: -21.773708 | AB30: 668272.15 | AC30: 120897.16 | AD30: 0 | AE30: 724.488 | AF30: 0 | AG30: 368451.94 | AH30: 179406.3 | AI30: 0 | AJ30: 270209.35 | AK30: 2123.702 | AL30: 370.935 | AM30: 474784.56 | AN30: 469000 | AO30: Commercio all'ingrosso non specializzato | AP30: 0 | AQ30: 17545.727 | AR30: 23774.561 | AS30: 0 | AT30: 151028.1 | AU30: 474784.56 | AV30: 272530.74 | AW30: 1452.353 | AX30: 43.778 | AY30: 24315.156
A31: 31. | B31: IPERAL SUPERMERCATI S.P.A. | C31: 11023300962 | D31: 45291 | E31: Dettagliato | F31: 1405942 | G31: 1397079 | H31: 0 | I31: 1019857.3 | J31: -1749.411 | K31: 113904.02 | L31: 114412.65 | M31: 3240.785 | N31: 21907.026 | O31: 24820.274 | P31: 0 | Q31: 0 | R31: 2832.443 | S31: 0 | T31: 0 | U31: 29629.077 | V31: 82752.702 | W31: 4193 | X31: 17.24626 | Y31: 33.92064 | Z31: 0 | AA31: 0 | AB31: 531958.26 | AC31: 27864.389 | AD31: 0 | AE31: 51022.823 | AF31: 0 | AG31: 298673.9 | AH31: 120255.72 | AI31: 0 | AJ31: 220620.12 | AK31: 0 | AL31: 77656.755 | AM31: 0 | AN31: 471120 | AO31: Supermercati | AP31: 0 | AQ31: 73633.384 | AR31: 97194.408 | AS31: 24780.912 | AT31: 191197.59 | AU31: 15000 | AV31: 220620.12 | AW31: 2631.713 | AX31: 1472.386
A32: 34. | B32: SUPERMERCATI TOSANO CEREA S.R.L. | C32: 01286680234 | D32: 45291 | E32: Dettagliato | F32: 1430571.6 | G32: 1418860.1 | H32: -1427.359 | I32: 1089893.7 | J32: -37702.227 | K32: 111843 | L32: 132961.78 | M32: 3808.74 | N32: 26942.495 | O32: 30872.979 | P32: 0 | Q32: 0 | R32: -10482.091 | S32: 0 | T32: 0 | U32: 13059.817 | V32: 48409.204 | W32: 3485 | X32: 18.197679 | Y32: 39.995527 | Z32: 49.547363 | AA32: 57.8563 | AB32: 1006898.8 | AC32: 71148.26 | AD32: 0 | AE32: 325964.18 | AF32: 0 | AG32: 400558.25 | AH32: 276521.47 | AI32: 0 | AJ32: 440685.91 | AK32: 278762.19 | AL32: 60106.157 | AM32: 0 | AN32: 471100 | AO32: Commercio al dettaglio in esercizi non specializzati con prevalenza di prodotti alimentari e bevande | AP32: 0 | AQ32: 24715.53 | AR32: 430910.37 | AS32: 31154.501 | AT32: 114655.44 | AU32: 0 | AV32: 597443.69 | AW32: 6188.529 | AX32: 19392.582 | AY32: 65137.781
A33: 35. | B33: PENNY MARKET S.R.L. | C33: 12619750156 | D33: 45291 | E33: Dettagliato | F33: 1543201.5 | G33: 1459033.3 | H33: 0 | I33: 1126355.3 | J33: -6595.698 | K33: 154834.78 | L33: 151886.7 | M33: 8640.149 | N33: 87497.612 | O33: 48860.117 | P33: 911.345 | Q33: 0 | R33: -5541.848 | S33: 8701.262 | T33: 0 | U33: -9309.64 | V33: -16719.713 | W33: 4483 | X33: 8.8454562 | Y33: 18.872335 | Z33: 24.099031 | AA33: -534.95955 | AB33: 572172.6 | AC33: 4923.246 | AD33: 0 | AE33: 108331.24 | AF33: 0 | AG33: 115081.04 | AH33: 228594.99 | AI33: 0 | AJ33: 444553.7 | AK33: 0 | AL33: 17143.074 | AM33: 0 | AN33: 471120 | AO33: Supermercati | AP33: 0 | AQ33: 69522.859 | AR33: 74002.126 | AS33: 263138.84 | AT33: 35549.572 | AU33: 0 | AV33: 444553.7 | AW33: 859.115 | AX33: 4484.893 | AY33: -4522.57
A34: 36. | B34: AGORA' NETWORK SOCIETA' CONSORTILE A R.L. | C34: 13211090157 | D34: 45291 | E34: Dettagliato | F34: 1390461.8 | G34: 1348280.4 | H34: 0 | I34: 1318454.3 | J34: -20463.202 | K34: 100084.55 | L34: 3887.151 | M34: 454.168 | N34: 580.098 | O34: 799.378 | P34: 0 | Q34: 0 | R34: 13530.377 | S34: 0 | T34: 0 | U34: 11.832 | V34: 183.889 | W34: 49 | X34: 16.602503 | Y34: 29.937058 | Z34: 61.84138 | AA34: 49.792434 | AB34: 333359.94 | AC34: 178999.94 | AD34: 0 | AE34: 131856.51 | AF34: 0 | AG34: 18479.802 | AH34: 164594.22 | AI34: 0 | AJ34: 257361.71 | AK34: 89414.116 | AL34: 1304.38 | AM34: 0 | AN34: 461904 | AO34: Gruppi di acquisto; mandatari agli acquisti; buyer | AP34: 0 | AQ34: 1213.321 | AR34: 4551.34 | AS34: 208.886 | AT34: 194041.4 | AU34: 0 | AV34: 313477.71 | AW34: 56.326 | AX34: 184.108 | AY34: -8368.432
A35: 37. | B35: IN'S MERCATO S.P.A. | C35: 02896940273 | D35: 45291 | E35: Dettagliato | F35: 1404190.9 | G35: 1393094.5 | H35: 0 | I35: 1011551.2 | J35: 5937.781 | K35: 115062.45 | L35: 113492.44 | M35: 10239.466 | N35: 56890.814 | O35: 48271.895 | P35: 950 | Q35: 1659.118 | R35: -348.95 | S35: 0 | T35: 0 | U35: 10396.178 | V35: 29390.581 | W35: 3886 | X35: 16.146717 | Y35: 34.728854 | Z35: 74.549959 | AA35: 107.17246 | AB35: 546428.13 | AC35: 4692.442 | AD35: 0 | AE35: 85973.854 | AF35: 0 | AG35: 199867.04 | AH35: 272988.32 | AI35: 0 | AJ35: 303275.77 | AK35: 35792.576 | AL35: 42037.216 | AM35: 10719.522 | AN35: 471130 | AO35: Discount di alimentari | AP35: 0 | AQ35: 173686.31 | AR35: 216160.48 | AS35: 3012.807 | AT35: 13267.007 | AU35: 10719.522 | AV35: 328100.04 | AW35: 5335.953 | AX35: 1570.935 | AY35: 42673.435
A36: 38. | B36: CONAD CENTRO NORD SOCIETA' COOPERATIVA | C36: 01751820356 | D36: 45291 | E36: Dettagliato | F36: 1564045.7 | G36: 1350867.3 | H36: 0 | I36: 1378249.8 | J36: -7694.86 | K36: 83039.306 | L36: 13368.226 | M36: 13054.62 | N36: 26698.634 | O36: 15532.585 | P36: 0 | Q36: 5943.633 | R36: 121.44 | S36: -2886.778 | T36: 0 | U36: 3492.478 | V36: 29596.021 | W36: 184 | X36: 6.9279277 | Y36: 13.729253 | Z36: 51.26353 | AA36: 10.338238 | AB36: 763451.31 | AC36: 66814.362 | AD36: 0 | AE36: 59928.236 | AF36: 0 | AG36: 351566.4 | AH36: 239529.71 | AI36: 0 | AJ36: 321854.76 | AK36: 99112.704 | AL36: 29445.076 | AM36: 0 | AN36: 461904 | AO36: Gruppi di acquisto; mandatari agli acquisti; buyer | AP36: 9417.687 | AQ36: 17383.145 | AR36: 284437.13 | AS36: 167080.86 | AT36: 183491.31 | AU36: 759.914 | AV36: 399198.74 | AW36: 1221.55 | AX36: 11507.957 | AY36: 46571.726
A37: 39. | B37: ALI' S.P.A. | C37: 00348980285 | D37: 45291 | E37: Dettagliato | F37: 1359569 | G37: 1348522.5 | H37: 0 | I37: 985872.35 | J37: -9340.974 | K37: 69962.487 | L37: 180407.79 | M37: 7129.962 | N37: 6352.147 | O37: 43541.772 | P37: 0 | Q37: 12141.358 | R37: 3650.062 | S37: -3283.328 | T37: 0 | U37: 15302.644 | V37: 48566.21 | W37: 4689 | X37: 9.2359723 | Y37: 16.027266 | Z37: 26.588238 | AA37: 33.033246 | AB37: 1085832 | AC37: 25149.3 | AD37: 0 | AE37: 109526.75 | AF37: 0 | AG37: 852090.41 | AH37: 147440.32 | AI37: 0 | AJ37: 202002.36 | AK37: 6.903 | AL37: 64561.189 | AM37: 0 | AN37: 471120 | AO37: Supermercati | AP37: 0 | AQ37: 2132.577 | AR37: 589016.81 | AS37: 1972.418 | AT37: 147051.96 | AU37: 169382.63 | AV37: 202055.51 | AW37: 3398.32 | AX37: 2187.678 | AY37: 80464.016
A38: 40. | B38: DIMAR S.P.A. | C38: 00294760046 | D38: 45291 | E38: Dettagliato | F38: 1346959.5 | G38: 1332694.6 | H38: 0 | I38: 967660.4 | J38: -6973.323 | K38: 119545.52 | L38: 119708.53 | M38: 6075.349 | N38: 11325.256 | O38: 64773.382 | P38: 1332.901 | Q38: 499.977 | R38: -214.43 | S38: 0 | T38: 0 | U38: 16675.342 | V38: 46121.72 | W38: 4331 | X38: 10.948423 | Y38: 18.813306 | Z38: 26.954541 | AA38: 60.721891 | AB38: 1001025.6 | AC38: 26768.002 | AD38: 0 | AE38: 107864.51 | AF38: 0 | AG38: 735437.96 | AH38: 138783.93 | AI38: 0 | AJ38: 238343.88 | AK38: 20059.195 | AL38: 69357.038 | AM38: 0 | AN38: 469000 | AO38: Commercio all'ingrosso non specializzato | AP38: 0 | AQ38: 15570.123 | AR38: 654412.82 | AS38: 78146.778 | AT38: 42796.847 | AU38: 20663.186 | AV38: 248901.05 | AW38: 7468.078 | AX38: 12214.284 | AY38: 79506.826
A39: 42. | B39: TIGROS REAL ESTATE S.P.A. | C39: 12790620152 | D39: 45291 | E39: Dettagliato | F39: 1245159.4 | G39: 1187345.1 | H39: -1337.248 | I39: 914433.67 | J39: -2602.132 | K39: 73961.314 | L39: 118415.77 | M39: 13862.375 | N39: 17666.07 | O39: 39613.786 | P39: 27.868 | Q39: 0 | R39: 3085.883 | S39: -1128.034 | T39: 0 | U39: 19104.7 | V39: 52633.834 | W39: 3391 | X39: 18.345907 | Y39: 34.183513 | Z39: 74.131542 | AA39: 112.67158 | AB39: 571787.8 | AC39: 43966.163 | AD39: 0 | AE39: 47648.964 | AF39: 0 | AG39: 366390.4 | AH39: 132115.41 | AI39: 0 | AJ39: 183048.74 | AK39: 29565.684 | AL39: 86302.312 | AM39: 15302.138 | AN39: 682001 | AO39: Locazione immobiliare di beni propri | AP39: 0 | AQ39: 19237.944 | AR39: 270890.7 | AS39: 27382.028 | AT39: 66447.806 | AU39: 47446.517 | AV39: 199345.77 | AW39: 3156.01 | AX39: 6431.536 | AY39: 51438.219
A40: 43. | B40: BUNGE ITALIA S.P.A. | C40: 01532980388 | D40: 45291 | E40: Dettagliato | F40: 1265540.1 | G40: 1282848.9 | H40: -27752.793 | I40: 1125735.2 | J40: -29196.921 | K40: 111534.79 | L40: 11136.28 | M40: 5232.543 | N40: 1503.762 | O40: 10167.356 | P40: 1030.48 | Q40: 0 | R40: -12158.069 | S40: 26337.658 | T40: 0 | U40: 2673.866 | V40: 39902.33 | W40: 157 | X40: 6.4799422 | Y40: 34.328217 | Z40: 80.314321 | AA40: -227.27618 | AB40: 396588.79 | AC40: 36172.231 | AD40: 0 | AE40: 169743.38 | AF40: 0 | AG40: 92316.115 | AH40: 41651.924 | AI40: 0 | AJ40: 250048.51 | AK40: 37735.727 | AL40: 20.077 | AM40: 0 | AN40: 104120 | AO40: Produzione di olio raffinato o grezzo da semi oleosi o frutti oleosi prevalentemente non di produzione propria | AP40: 0 | AQ40: 342.612 | AR40: 78120.929 | AS40: 2950.005 | AT40: 55109.171 | AU40: 89482.193 | AV40: 250048.51 | AW40: 0 | AX40: 820.425 | AY40: -30299.435
A41: 44. | B41: COCA-COLA HBC ITALIA S.R.L. | C41: 12363410155 | D41: 45291 | E41: Dettagliato | F41: 1326233.5 | G41: 1273920.7 | H41: -3543.748 | I41: 734969.93 | J41: 4586.243 | K41: 243057.77 | L41: 153016.33 | M41: 7187.289 | N41: 23101.191 | O41: 34040.175 | P41: 0 | Q41: 0 | R41: 133641.08 | S41: 1561.488 | T41: 0 | U41: 41257.903 | V41: 220219.27 | W41: 2001 | X41: 10.966221 | Y41: 36.030205 | Z41: 35.806324 | AA41: 55.37752 | AB41: 1780839.7 | AC41: 250773.79 | AD41: 0 | AE41: 83872.939 | AF41: 1800 | AG41: 987779.92 | AH41: 167899.9 | AI41: 0 | AJ41: 755545.32 | AK41: 0 | AL41: 510.087 | AM41: 88547.579 | AN41: 110700 | AO41: Industria delle bibite analcoliche, delle acque minerali e di altre acque in bottiglia | AP41: 0 | AQ41: 35461.174 | AR41: 274243.81 | AS41: 1011321.7 | AT41: 280872.92 | AU41: 91081.568 | AV41: 755545.32 | AW41: 6298.201 | AX41: 1675.526 | AY41: 103177.59
A42: 45. | B42: CONAD ADRIATICO SOCIETA' COOPERATIVA | C42: 00105820443 | D42: 45291 | E42: Dettagliato | F42: 1343059 | G42: 1194099.3 | H42: 0 | I42: 1197196.3 | J42: -2298.573 | K42: 84016.371 | L42: 12657.292 | M42: 3211.865 | N42: 5701.301 | O42: 4479.656 | P42: 0 | Q42: 685.428 | R42: 4375.716 | S42: -1000 | T42: 0 | U42: 5739.185 | V42: 35045.927 | W42: 339 | X42: 7.8274911 | Y42: 15.955451 | Z42: 50.133546 | AA42: 87.235372 | AB42: 575588.24 | AC42: 102629.32 | AD42: 0 | AE42: 47991.615 | AF42: 0 | AG42: 285871.77 | AH42: 179243.53 | AI42: 0 | AJ42: 198316.52 | AK42: 91387.614 | AL42: 1668.063 | AM42: 126638.44 | AN42: 463920 | AO42: Commercio all'ingrosso non specializzato di prodotti alimentari, bevande e tabacco | AP42: 443.266 | AQ42: 3690.623 | AR42: 7023.007 | AS42: 213337.69 | AT42: 172521.15 | AU42: 126638.44 | AV42: 283926.79 | AW42: 723.788 | AX42: 2274.39 | AY42: 22372.403
A43: 46. | B43: GRANAROLO S.P.A. IN SIGLA G. SPA | C43: 04119190371 | D43: 45291 | E43: Dettagliato | F43: 1207872 | G43: 1172535 | H43: 27463 | I43: 846101 | J43: 1457 | K43: 200625 | L43: 88883 | M43: 7183 | N43: 6485 | O43: 43638 | P43: 0 | Q43: 156 | R43: -10685 | S43: 0 | T43: 0 | U43: -5053 | V43: 7712 | W43: 1272 | X43: 10.524232 | Y43: 26.383167 | Z43: 23.200771 | AA43: 11.432259 | AB43: 1339820 | AC43: 56970 | AD43: 0 | AE43: 124596 | AF43: 0 | AG43: 350640 | AH43: 315328 | AI43: 0 | AJ43: 640885 | AK43: 497433 | AL43: 130704 | AM43: 0 | AN43: 105110 | AO43: Trattamento igienico del latte | AP43: 0 | AQ43: 113182 | AR43: 353587 | AS43: 214002 | AT43: 403749 | AU43: 0 | AV43: 961452 | AW43: 9167 | AX43: 0 | AY43: 51136
... A59: 63. | B59: UNIGRA' S.P.A. | C59: 02403240399 | D59: 45291 | E59: Dettagliato | F59: 1009075.5 | G59: 947278.88 | H59: -38060.845 | I59: 653476.53 | J59: 3923.232 | K59: 194657.87 | L59: 46660.209 | M59: 7518.604 | N59: 8763.482 | O59: 19467.334 | P59: 121.909 | Q59: 25000 | R59: -14041.747 | S59: -6062.447 | T59: 0 | U59: 9444.057 | V59: 19938.055 | W59: 738 | X59: -8.5950046 | Y59: 33.426357 | Z59: 78.745414 | AA59: -0.11412463 | AB59: 916935.96 | AC59: 97757.403 | AD59: 616.432 | AE59: 197132.83 | AF59: 0 | AG59: 394483.03 | AH59: 154342.43 | AI59: 0 | AJ59: 392927.99 | AK59: 302241.35 | AL59: 81419.398 | AM59: 0 | AN59: 104120 | AO59: Produzione di olio raffinato o grezzo da semi oleosi o frutti oleosi prevalentemente non di produzione propria | AP59: 0 | AQ59: 36134.789 | AR59: 148350.39 | AS59: 257603.16 | AT59: 187621.7 | AU59: 4875.736 | AV59: 485486.82 | AW59: 2605.586 | AX59: 3797.96 | AY59: 69032.423
A60: 64. | B60: NESTLE' ITALIANA S.P.A. IN FORMA ABBREVIATA NE.IT. S.P.A. | C60: 00777280157 | D60: 45291 | E60: Dettagliato | F60: 972013 | G60: 971754 | H60: 0 | I60: 475580 | J60: 0 | K60: 280567 | L60: 132370 | M60: 9989 | N60: 0 | O60: 25605 | P60: 573 | Q60: 0 | R60: 14434 | S60: 0 | T60: 15617 | U60: 11793 | V60: 65587 | W60: 2005 | X60: 7.4844484 | Y60: 15.40994 | Z60: 0 | AA60: 0 | AB60: 627703 | AC60: 167742 | AD60: 0 | AE60: 73106 | AF60: 0 | AG60: 116306 | AH60: 231734 | AI60: 0 | AJ60: 404558 | AK60: 26688 | AL60: 3 | AM60: 0 | AN60: 100000 | AO60: Industrie alimentari | AP60: 0 | AQ60: 13166 | AR60: 138152 | AS60: 90161 | AT60: 313115 | AU60: 0 | AV60: 491189 | AW60: 1040 | AX60: 0
A61: 65. | B61: BIG S.R.L. | C61: 04492200961 | D61: 45291 | E61: Dettagliato | F61: 905827 | G61: 904542 | H61: 0 | I61: 667341 | J61: 3118 | K61: 144736 | L61: 52080 | M61: 583 | N61: 912 | O61: 9311 | P61: 0 | Q61: 0 | R61: 4638 | S61: 0 | T61: 0 | U61: 7649 | V61: 24735 | W61: 807 | X61: 5.5690485 | Y61: 17.250668 | Z61: 15.755002 | AA61: -8.2020412 | AB61: 740472 | AC61: 37613 | AD61: 0 | AE61: 23179 | AF61: 0 | AG61: 463244 | AH61: 34357 | AI61: 0 | AJ61: 223443 | AK61: 140630 | AL61: 3286 | AM61: 194564 | AN61: 463310 | AO61: Commercio all'ingrosso di prodotti lattiero-caseari e di uova | AP61: 0 | AQ61: 313680 | AR61: 50879 | AS61: 88 | AT61: 60955 | AU61: 288368 | AV61: 262761 | AW61: 0 | AX61: 37 | AY61: 40368
A62: 66. | B62: SALUMIFICI GRANTERRE S.P.A. | C62: 02654810361 | D62: 45291 | E62: Dettagliato | F62: 896178 | G62: 865693 | H62: 8076 | I62: 618523 | J62: -108 | K62: 137147 | L62: 91358 | M62: 4097 | N62: 1826 | O62: 27621 | P62: 0 | Q62: 294 | R62: -15677 | S62: 847 | T62: 760 | U62: -1662 | V62: 3012 | W62: 1403 | X62: 10.05029 | Y62: 22.557953 | Z62: 31.325385 | AA62: 21.440664 | AB62: 726189 | AC62: 33693 | AD62: 0 | AE62: 160707 | AF62: 0 | AG62: 166717 | AH62: 216664 | AI62: 0 | AJ62: 452611 | AK62: 259889 | AL62: 131899 | AM62: 0 | AN62: 101300 | AO62: Produzione di prodotti a base di carne (inclusa la carne di volatili) | AP62: 0 | AQ62: 129214 | AR62: 209161 | AS62: 4483 | AT62: 88062 | AU62: 821 | AV62: 542915 | AW62: 3081 | AX62: 1842 | AY62: 35442
A63: 67. | B63: CONSERVE ITALIA - CONSORZIO ITALIANO FRA COOPERATIVE AGRICOLE - S OCIETA' COOPERATIVA AGRICOLA - IN FORMA ABBREVIATA CONSERVE ITALIA SOC.COOP. AG RICOLA . | C63: 00708311204 | D63: 45107 | E63: Dettagliato | F63: 863870.24 | G63: 836755.27 | H63: -454.27 | I63: 479932.72 | J63: -5759.907 | K63: 244926.71 | L63: 79653.979 | M63: 2835.061 | N63: 10949.06 | O63: 30829.366 | P63: 280 | Q63: 0 | R63: -13543.036 | S63: 0 | T63: 0 | U63: 12.309 | V63: 6667.899 | W63: 2144 | X63: 19.568423 | Y63: 33.736204 | Z63: 32.534358 | AA63: 85.932508 | AB63: 874850.98 | AC63: 64345.526 | AD63: 0 | AE63: 196346.83 | AF63: 0 | AG63: 293481.61 | AH63: 223755.3 | AI63: 0 | AJ63: 432549.75 | AK63: 211009.58 | AL63: 115897.07 | AM63: 0 | AN63: 103000 | AO63: Lavorazione e conservazone di frutta e ortaggi | AP63: 361.5 | AQ63: 50150.658 | AR63: 298649.9 | AS63: 107299.38 | AT63: 104021.27 | AU63: 0 | AV63: 547761.54 | AW63: 10277.3 | AX63: 2124.367 | AY63: 27457.603
A64: 68. | B64: UNICOOP ETRURIA SOCIETA' COOPERATIVA | C64: 00103530499 | D64: 45291 | E64: Dettagliato | F64: 937600.55 | G64: 919095.14 | H64: 0 | I64: 653266.67 | J64: 4100.076 | K64: 95093.082 | L64: 119402.2 | M64: 15888.135 | N64: 20389.148 | O64: 21318.79 | P64: 155.8 | Q64: 952.358 | R64: 1156.28 | S64: -7248.932 | T64: 0 | U64: -151.672 | V64: 1093.306 | W64: 3268 | X64: 0.61991248 | Y64: 4.5550237 | Z64: 1.7720036 | AA64: 356.00226 | AB64: 1312192.5 | AC64: 64314.136 | AD64: 844.133 | AE64: 45160.175 | AF64: 0 | AG64: 272829.89 | AH64: 150386.39 | AI64: 388.022 | AJ64: 895446.91 | AK64: 783112.83 | AL64: 20892.872 | AM64: 801.557 | AN64: 471100 | AO64: Commercio al dettaglio in esercizi non specializzati con prevalenza di prodotti alimentari e bevande | AP64: 0 | AQ64: 148902.24 | AR64: 444414.41 | AS64: 455430.18 | AT64: 130744.63 | AU64: 63308.729 | AV64: 995056.11 | AW64: 8355.779 | AX64: 3339.294 | AY64: 6217.749
A65: 69. | B65: FERRERO INDUSTRIALE ITALIA S.R.L. | C65: 03629080049 | D65: 45169 | E65: Dettagliato | F65: 869727 | G65: 805718 | H65: 0 | I65: 62200 | J65: 0 | K65: 324331 | L65: 276367 | M65: 5153 | N65: 682 | O65: 120428 | P65: 8608 | Q65: 0 | R65: -4875 | S65: 0 | T65: 0 | U65: 10588 | V65: 56495 | W65: 5330 | X65: 7.6686653 | Y65: 20.256597 | Z65: 29.440096 | AA65: 26.124153 | AB65: 1401204 | AC65: 1476 | AD65: 0 | AE65: 26125 | AF65: 0 | AG65: 856076 | AH65: 123286 | AI65: 0 | AJ65: 494540 | AK65: 16976 | AL65: 54 | AM65: 0 | AN65: 108200 | AO65: Produzione di cacao in polvere, cioccolato, caramelle e confetterie | AP65: 0 | AQ65: 88 | AR65: 1122619 | AS65: 113 | AT65: 234068 | AU65: 0 | AV65: 505900 | AW65: 10017 | AX65: 18137 | AY65: 152537
A66: 70. | B66: AVI.COOP SOCIETA' COOPERATIVA AGRICOLA IN BREVE: AVI.COOP S.C.A. OVVERO: AVI.COOP SOC. COOP. AGR. | C66: 01247140401 | D66: 45291 | E66: Dettagliato | F66: 837376.46 | G66: 827415.52 | H66: -1490.023 | I66: 625295.4 | J66: -1359.124 | K66: 58830.671 | L66: 127227.82 | M66: 578.856 | N66: 8657.432 | O66: 12883.658 | P66: 0 | Q66: 0 | R66: -5205.937 | S66: 0 | T66: 0 | U66: 0.603 | V66: 55.205 | W66: 5481 | X66: -2.2380724 | Y66: 27.526003 | Z66: 69.549139 | AA66: 141.02484 | AB66: 206571.24 | AC66: 43877.561 | AD66: 0 | AE66: 13121.923 | AF66: 0 | AG66: 8335.069 | AH66: 39869.184 | AI66: 0 | AJ66: 179487.08 | AK66: 0.022 | AL66: 11.353 | AM66: 0 | AN66: 016300 | AO66: Attività che seguono la raccolta | AP66: 0 | AQ66: 1004.733 | AR66: 126312.04 | AS66: 12327.736 | AT66: 52125.444 | AU66: 0 | AV66: 179487.08 | AW66: 9583.425 | AX66: 1668.011 | AY66: 7528.437
A67: 71. | B67: HEINEKEN ITALIA SPA | C67: 00610140071 | D67: 45291 | E67: Dettagliato | F67: 855632 | G67: 826616 | H67: -17483 | I67: 390614 | J67: 0 | K67: 202318 | L67: 84919 | M67: 8713 | N67: 0 | O67: 35256 | P67: 1105 | Q67: 0 | R67: -5895 | S67: 0 | T67: 0 | U67: 35273 | V67: 91539 | W67: 1102 | X67: 9.716913 | Y67: 21.771591 | Z67: 32.10384 | AA67: 20.484771 | AB67: 710098 | AC67: 20253 | AD67: 0 | AE67: 78751 | AF67: 0 | AG67: 236362 | AH67: 136497 | AI67: 0 | AJ67: 267207 | AK67: 25287 | AL67: 6063 | AM67: 158592 | AN67: 110500 | AO67: Produzione di birra | AP67: 0 | AQ67: 4127 | AR67: 228525 | AS67: 140755 | AT67: 92622 | AU67: 158592 | AV67: 455762 | AW67: 1932 | AX67: 663 | AY67: 139406
A68: 72. | B68: MAIORA SOCIETA' PER AZIONI | C68: 07390770720 | D68: 45291 | E68: Dettagliato | F68: 832391 | G68: 825297 | H68: 0 | I68: 635633 | J68: -1025 | K68: 61351 | L68: 71944 | M68: 4738 | N68: 5629 | O68: 25780 | P68: 0 | Q68: 0 | R68: -1129 | S68: 0 | T68: -658 | U68: 6907 | V68: 19647 | W68: 2626 | X68: 7.3652043 | Y68: 15.09985 | Z68: 38.051547 | AA68: 52.226254 | AB68: 370350 | AC68: 26076 | AD68: 0 | AE68: 65590 | AF68: 0 | AG68: 89314 | AH68: 134606 | AI68: 0 | AJ68: 179216 | AK68: 93035 | AL68: 46818 | AM68: 0 | AN68: 469000 | AO68: Commercio all'ingrosso non specializzato | AP68: 0 | AQ68: 76437 | AR68: 129674 | AS68: 2561 | AT68: 41651 | AU68: 0 | AV68: 264819 | AW68: 11551 | AX68: 7619 | AY68: 35553
A69: 74. | B69: CASEIFICI GRANTERRE SPA | C69: 01299680353 | D69: 45291 | E69: Dettagliato | F69: 731727 | G69: 727439 | H69: -1191 | I69: 617968 | J69: -1212 | K69: 50264 | L69: 33391 | M69: 927 | N69: 412 | O69: 8894 | P69: 170 | Q69: 0 | R69: -11148 | S69: 0 | T69: 20 | U69: 3173 | V69: 6612 | W69: 532 | X69: 5.370508 | Y69: 19.087135 | Z69: 78.039032 | AA69: 59.583467 | AB69: 522573 | AC69: 122683 | AD69: 0 | AE69: 251054 | AF69: 0 | AG69: 53989 | AH69: 174078 | AI69: 0 | AJ69: 373112 | AK69: 271712 | AL69: 57481 | AM69: 0 | AN69: 463310 | AO69: Commercio all'ingrosso di prodotti lattiero-caseari e di uova | AP69: 0 | AQ69: 4158 | AR69: 56885 | AS69: 957 | AT69: 151139 | AU69: 0 | AV69: 460446 | AW69: 2020 | AX69: 899 | AY69: 18678
A70: 75. | B70: COOP LIGURIA SOCIETA' COOPERATIVA DI CONSUMO | C70: 00103220091 | D70: 45291 | E70: Dettagliato | F70: 834708.63 | G70: 820690.63 | H70: 0 | I70: 597251.65 | J70: -54.94 | K70: 86106.216 | L70: 92148.29 | M70: 6352.886 | N70: 34685.215 | O70: 14516.798 | P70: 0 | Q70: 4037.502 | R70: 30912.419 | S70: -17796.118 | T70: 0 | U70: 2396.1 | V70: 10385.21 | W70: 2732 | X70: 3.4362661 | Y70: 9.3962829 | Z70: 8.3881136 | AA70: 342.59959 | AB70: 1658098.9 | AC70: 5459.738 | AD70: 0 | AE70: 36556.039 | AF70: 0 | AG70: 779190.74 | AH70: 18449.788 | AI70: 0 | AJ70: 768947.36 | AK70: 759495.97 | AL70: 51877.609 | AM70: 0 | AN70: 471120 | AO70: Supermercati | AP70: 0 | AQ70: 8077.117 | AR70: 40800.098 | AS70: 452084.97 | AT70: 414349.91 | AU70: 647647.59 | AV70: 846504.09 | AW70: 2350.744 | AX70: 6705.617 | AY70: 3204.207
A71: 76. | B71: APULIA DISTRIBUZIONE S.R.L. | C71: 05754810728 | D71: 45291 | E71: Dettagliato | F71: 819823.19 | G71: 805167.71 | H71: 0 | I71: 722819.08 | J71: -4676.139 | K71: 48057.989 | L71: 13321.443 | M71: 13421.738 | N71: 9835.529 | O71: 5916.234 | P71: 1273.378 | Q71: 0 | R71: -119.677 | S71: -249.998 | T71: 0 | U71: 8922.328 | V71: 561.937 | W71: 327 | X71: 0.08254394 | Y71: 27.243624 | Z71: 33.311329 | AA71: -18.825017 | AB71: 331965.48 | AC71: 83134.287 | AD71: 0 | AE71: 53048.793 | AF71: 0 | AG71: 118345.15 | AH71: 141041.51 | AI71: 0 | AJ71: 170256.78 | AK71: 37840.606 | AL71: 45474.118 | AM71: 0 | AN71: 463920 | AO71: Commercio all'ingrosso non specializzato di prodotti alimentari, bevande e tabacco | AP71: 0 | AQ71: 10625.087 | AR71: 53216.805 | AS71: 4549.059 | AT71: 131540.52 | AU71: 31555.438 | AV71: 207667.29 | AW71: 2018.209 | AX71: 1955.662 | AY71: 19427.382
A72: 77. | B72: ROSSETTO TRADE S.P.A. | C72: 02928530233 | D72: 45291 | E72: Dettagliato | F72: 752139.83 | G72: 745972.89 | H72: 0 | I72: 540840.87 | J72: 7029.153 | K72: 45333.295 | L72: 89430.348 | M72: 1687.163 | N72: 28889.455 | O72: 9098.355 | P72: 300 | Q72: 0 | R72: 1338.015 | S72: 0 | T72: 0 | U72: 7993.302 | V72: 22875.908 | W72: 1825 | X72: 16.808231 | Y72: 30.003401 | Z72: 49.620299 | AA72: 50.033285 | AB72: 267374.04 | AC72: 27920.346 | AD72: 0 | AE72: 79175.694 | AF72: 0 | AG72: 137356.66 | AH72: 98339.507 | AI72: 0 | AJ72: 120307.04 | AK72: 24.09 | AL72: 65083.09 | AM72: 0 | AN72: 471100 | AO72: Commercio al dettaglio in esercizi non specializzati con prevalenza di prodotti alimentari e bevande | AP72: 0 | AQ72: 15189.749 | AR72: 25334.067 | AS72: 31182.223 | AT72: 45982.646 | AU72: 0 | AV72: 120307.04 | AW72: 2624.75 | AX72: 5426.568 | AY72: 25747.32
... A80: 87. | B80: CASA OLEARIA ITALIANA SOCIETA' PER AZIONI IN SIGLA CASA OLEARIA ITALIANA S.P.A. | C80: 01458780747 | D80: 45291 | E80: Dettagliato | F80: 503736.32 | G80: 494860.92 | H80: -83.54 | I80: 415486.37 | J80: 5536.582 | K80: 14474.142 | L80: 2269.755 | M80: 493.258 | N80: 977.192 | O80: 4253.237 | P80: 0 | Q80: 0 | R80: 6018.02 | S80: 13449.55 | T80: 0 | U80: 16419.536 | V80: 63293.815 | W80: 43 | X80: 29.310387 | Y80: 77.052273 | Z80: 116.8046 | AA80: 1015.1213 | AB80: 519780.19 | AC80: 66518.948 | AD80: 1.214 | AE80: 89896.271 | AF80: 0 | AG80: 425586.64 | AH80: 51904.965 | AI80: 0 | AJ80: 92159.315 | AK80: 12929.518 | AL80: 340.697 | AM80: 178285.66 | AN80: 104120 | AO80: Produzione di olio raffinato o grezzo da semi oleosi o frutti oleosi prevalentemente non di produzione propria | AP80: 0 | AQ80: 284.565 | AR80: 25960.515 | AS80: 87837.954 | AT80: 137145.58 | AU80: 178285.66 | AV80: 92159.315 | AW80: 1061.225 | AX80: 28.949 | AY80: 5784.036

Sheet calcoli
A1: Gruppo | B1: Ragione sociale | C1: P.Iva | D1: Anno | E1: Tipo di bilancio | F1: Classe | G1: Sottoclasse | H1: Nota Generale | I1: Fatturato | L1: Fatturato (100%) +/- Δ Rimanenze Prodotti | O1: Consumo di Materie Prime | R1: margine commerciale PURO | U1: Altri ricavi | X1: Margine Commerciale/I0USTRIALE | AA1: Spese per Servizi | AD1: Costo del lavoro | AG1: +/- Altri Costi e Ricavi Operativi | AJ1: EBITDAR | AM1: Spese per affitti e noleggi | AP1: EBITDA margin | AS1: Ammortamenti e Svalutazioni | AV1: EBIT margin | AY1: Gestione finanziaria (interessi e rettifiche) | BB1: Gestione straordinaria | BE1: Imposte | BH1: Profit margin | BK1: Crescita Fatturato ultimo anno | BL1: Crescita Fatturato a 3 anni | BM1: Crescita Fatturato a 5 anni | BN1: crescita EBITDA 5 anni | BO1: Risultato d'Esercizio / Ricavi | BP1: ROI | BQ1: ROE | BR1: Profit Margin | BS1: Rotazione Attivo | BT1: Leva Finanziaria | BU1: Tempi medi giacenza Scorte (rimanenze/Fatturato)*360 | BV1: Tempi medi incasso (Clienti/Fatturato)*360 | BW1: Tempi medi pagamento (Fornitori/(Acquisti+Servizi+Affitti e noleggi))*360 | BX1: mezzi propri/attivo | BY1: debiti finanziari netti/ricavi | BZ1: Debiti a breve/ricavi | CA1: Aggregato | CB1: Crediti vs Soci | CC1: % | CD1: Immobilizzi immateriali | CE1: % | CF1: Immobilizzi materiali | CG1: % | CH1: Immobilizzi finanziari | CI1: % | CJ1: Totale Attivo Immobilizzato | CK1: % | CL1: Rimanenze | CM1: % | CN1: Crediti | CO1: % | CP1: Attività Finanziarie correnti | CQ1: % | CR1: Disponibilità Liquide | CS1: % | CT1: Totale Attivo Corrente | CU1: % | CV1: Ratei e Risconti Attivi | CW1: % | CX1: Totale Attivo | CY1: % | CZ1: Patrimonio Netto | DA1: % | DB1: Fondo TFR e Fondi Rischi | DC1: % | DD1: Debiti | DE1: % | DF1: di cui a breve termine | DG1: % | DH1: di cui a medio lungo termine | DI1: % | DJ1: Ratei e Risconti Passivi | DK1: % | DL1: Totale Passivo | DM1: %
I2: Valore | J2: % | K2: Nota | L2: Valore | M2: % | N2: Nota | O2: Valore | P2: % | Q2: Nota | R2: Valore | S2: % | T2: Nota | U2: Valore | V2: % | W2: Nota | X2: Valore | Y2: % | Z2: Nota | AA2: Valore | AB2: % | AC2: Nota | AD2: Valore | AE2: % | AF2: Nota | AG2: Valore | AH2: % | AI2: Nota | AJ2: Valore | AK2: % | AL2: Nota | AM2: Valore | AN2: % | AO2: Nota | AP2: Valore | AQ2: % | AR2: Nota | AS2: Valore | AT2: % | AU2: Nota | AV2: Valore | AW2: % | AX2: Nota | AY2: Valore | AZ2: % | BA2: Nota | BB2: Valore | BC2: % | BD2: Nota | BE2: Valore | BF2: % | BG2: Nota | BH2: Valore | BI2: % | BJ2: Nota
B3: =+Risultati!B2 -> ESSELUNGA SPA | C3: =+Risultati!C2 -> 04916380159 | D3: =IF(YEAR(Risultati!D2)=1900,(MID(Risultati!$AP$1,29,4)),YEAR(Risultati!D2)) -> 2023 | E3: =+Risultati!E2 -> Dettagliato | F3: =(LEFT(Risultati!AN2,2)&"-")&VLOOKUP((LEFT(Risultati!AN2,2)),ateco!$B$4:$C$93,2,FALSE) -> 47-Commercio al dettaglio (escluso quello di autoveicoli e di motocicli) | G3: =SUBSTITUTE((Risultati!AN2&"-"&Risultati!AO2),",",";") -> 471100-Commercio al dettaglio in esercizi non specializzati con prevalenza di prodotti alimentari e bevande | I3: =+Risultati!G2 -> 9038616 | J3: =IF(L3<>0,(I3/L3),"0") -> 1 | L3: =+Risultati!G2+Risultati!H2 -> 9038616 | M3: =IF(L3<>0,(L3/(L3+U3)),"0") -> 0.99100612 | O3: =+Risultati!I2+Risultati!J2 -> 6285561 | P3: =IF(L3<>0,(O3/(L3+U3)),"0") -> 0.68915743 | R3: =+L3-O3 -> 2753055 | S3: =IF(L3<>0,(R3/(L3+U3)),"0") -> 0.30184868 | U3: =+Risultati!F2-(Risultati!G2+Risultati!H2) -> 82030 | V3: =IF(L3<>0,(U3/(L3+U3)),"0") -> 0.0089938805 | X3: =+U3+R3 -> 2835085 | Y3: =IF(L3<>0,(X3/(L3+U3)),"0") -> 0.31084257 | AA3: =+Risultati!K2 -> 1015920 | AB3: =IF(L3<>0,(AA3/(L3+U3)),"0") -> 0.11138685 | AD3: =+Risultati!L2 -> 1052480 | AE3: =IF(L3<>0,(AD3/(L3+U3)),"0") -> 0.11539533 | AG3: =+Risultati!M2+Risultati!P2+Risultati!Q2 -> 122827 | AH3: =IF(L3<>0,(AG3/(L3+U3)),"0") -> 0.013466919 | AJ3: =+X3-AA3-AD3-AG3 -> 643858 | AK3: =IF(L3<>0,(AJ3/(L3+U3)),"0") -> 0.070593465 | AM3: =+Risultati!N2 -> 25090 | AN3: =IF(L3<>0,(AM3/(L3+U3)),"0") -> 0.0027509016 | AP3: =+AJ3-AM3 -> 618768 | AQ3: =IF(L3<>0,(AP3/(L3+U3)),"0") -> 0.067842563 | AS3: =+Risultati!O2 -> 406552 | AT3: =IF(L3<>0,(AS3/(L3+U3)),"0") -> 0.044574913 | AV3: =+AP3-AS3 -> 212216 | AW3: =IF(L3<>0,(AV3/(L3+U3)),"0") -> 0.02326765 | AY3: =+Risultati!R2+Risultati!S2 -> -44934 | AZ3: =IF(L3<>0,(AY3/(L3+U3)),"0") -> -0.0049266247 | BB3: =+Risultati!T2 -> 1031 | BC3: =IF(L3<>0,(BB3/(L3+U3)),"0") -> 0.00011304024 | BE3: =+Risultati!U2 -> 39284 | BF3: =IF(L3<>0,(BE3/(L3+U3)),"0") -> 0.0043071511 | BH3: =+AV3+AY3+BB3-BE3 -> 129029 | BI3: =IF(L3<>0,(+BH3/(L3+U3)),"0") -> 0.014146915 | BK3: =IF(ISNUMBER(Risultati!X2/100),(Risultati!X2/100)) -> 0.05910202 | BL3: =IF(ISNUMBER(Risultati!Y2/100),(Risultati!Y2/100)) -> 0.071247441 | BM3: =IF(ISNUMBER(Risultati!Z2/100),(Risultati!Z2/100)) -> 0.14224044 | BN3: =IF(AND(Risultati!AY2<0,calcoli!AP3<0),-IF(ISNUMBER(Risultati!AA2/100),(Risultati!AA2/100)),IF(ISNUMBER(Risultati!AA2/100),(Risultati!AA2/100))) -> -0.11973027 | BO3: =+BI3 -> 0.014146915 | BP3: =IF(Risultati!AB2>0,(AV3/Risultati!AB2),"0") -> 0.026894878 | BQ3: =IF(Risultati!AG2<>0,(BH3/Risultati!AG2),"0") -> 0.058628439 | BR3: =+BI3 -> 0.014146915 | BS3: =IF(Risultati!AB2>0,(Risultati!G2/Risultati!AB2),"0") -> 1.1454955 | BT3: =IF(Risultati!AG2<>0,(Risultati!AB2/Risultati!AG2),"0") -> 3.5853334 | BU3: =IF(AND(Risultati!G2>0,(Risultati!AE2-Risultati!AF2)>=0),((Risultati!AE2-Risultati!AF2)/Risultati!G2*360),"0") -> 22.529374 | BV3: =IF(OR(E3="abbreviato",Risultati!G2=0),"0",((Risultati!AC2+Risultati!AD2)/Risultati!G2*360)) -> 10.484216 | BW3: =IF(OR(E3="abbreviato",Risultati!G2=0,SUM(Risultati!I2+Risultati!K2+Risultati!M2)=0),"0",(((Risultati!AH2+Risultati!AI2)/(Risultati!I2+Risultati!K2+Risultati!N2)*360))) -> 83.190027 | BX3: =IF(Risultati!AB2>0,(+Risultati!AG2/Risultati!AB2),"0") -> 0.27891409 | BY3: =IF(OR(E3="abbreviato",Risultati!G2=0),"0",(((Risultati!AK2-(Risultati!AL2+Risultati!AM2))/Risultati!G2))) -> 0.32164758 | BZ3: =IF(Risultati!G2>0,(Risultati!AJ2/Risultati!G2),"0") -> 0.26104417 | CB3: =+Risultati!AP2 -> 0 | CC3: =IF($CX3>0,(CB3/$CX3),"0") -> 0 | CD3: =+Risultati!AQ2 -> 220145 | CE3: =IF($CX3>0,(CD3/$CX3),"0") -> 0.027899748 | CF3: =+Risultati!AR2 -> 5222483 | CG3: =IF($CX3>0,(CF3/$CX3),"0") -> 0.66186359 | CH3: =+Risultati!AS2 -> 1159374 | CI3: =IF($CX3>0,(CH3/$CX3),"0") -> 0.14693153 | CJ3: =+CH3+CF3+CD3 -> 6602002 | CK3: =IF($CX3>0,(CJ3/$CX3),"0") -> 0.83669488 | CL3: =+Risultati!AE2+Risultati!AF2 -> 565651 | CM3: =IF($CX3>0,(CL3/$CX3),"0") -> 0.071686936 | CN3: =+Risultati!AT2 -> 402192 | CO3: =IF($CX3>0,(CN3/$CX3),"0") -> 0.050971203 | CP3: =+Risultati!AU2 -> 53307 | CQ3: =IF($CX3>0,(CP3/$CX3),"0") -> 0.0067557831 | CR3: =+Risultati!AL2 -> 252746 | CS3: =IF($CX3>0,(CR3/$CX3),"0") -> 0.032031387 | CT3: =+CR3+CP3+CN3+CL3 -> 1273896 | CU3: =IF($CX3>0,(CT3/$CX3),"0") -> 0.16144531 | CV3: =+Risultati!AX2 -> 14675 | CW3: =IF($CX3>0,(CV3/$CX3),"0") -> 0.0018598142 | CX3: =+CV3+CT3+CJ3 -> 7890573 | CY3: =IF($CX3>0,(CX3/$CX3),"0") -> 1 | CZ3: =+Risultati!AG2 -> 2200792 | DA3: =IF($CX3>0,(CZ3/$CX3),"0") -> 0.27891409 | DB3: =+DL3-CZ3-DD3-DJ3 -> 118851 | DC3: =IF($CX3>0,(DB3/$CX3),"0") -> 0.015062404 | DD3: =+Risultati!AV2 -> 5393411 | DE3: =IF($CX3>0,(DD3/$CX3),"0") -> 0.6835259 | DF3: =+Risultati!AJ2 -> 2359478 | DG3: =IF($CX3>0,(DF3/$CX3),"0") -> 0.29902493 | DH3: =+DD3-DF3 -> 3033933 | DI3: =IF($CX3>0,(DH3/$CX3),"0") -> 0.38450097 | DJ3: =+Risultati!AW2 -> 177519 | DK3: =IF($CX3>0,(DJ3/$CX3),"0") -> 0.022497606 | DL3: =+CX3 -> 7890573 | DM3: =IF($CX3>0,(DL3/$CX3),"0") -> 1
B4: =+Risultati!B3 -> LIDL ITALIA S.R.L. | C4: =+Risultati!C3 -> 02275030233 | D4: =IF(YEAR(Risultati!D3)=1900,(MID(Risultati!$AP$1,29,4)),YEAR(Risultati!D3)) -> 2024 | E4: =+Risultati!E3 -> Dettagliato | F4: =(LEFT(Risultati!AN3,2)&"-")&VLOOKUP((LEFT(Risultati!AN3,2)),ateco!$B$4:$C$93,2,FALSE) -> 46-Commercio all'ingrosso (escluso quello di autoveicoli e di motocicli) | G4: =SUBSTITUTE((Risultati!AN3&"-"&Risultati!AO3),",",";") -> 469000-Commercio all'ingrosso non specializzato | I4: =+Risultati!G3 -> 7158326 | J4: =IF(L4<>0,(I4/L4),"0") -> 1 | L4: =+Risultati!G3+Risultati!H3 -> 7158326 | M4: =IF(L4<>0,(L4/(L4+U4)),"0") -> 0.99005495 | O4: =+Risultati!I3+Risultati!J3 -> 5244243 | P4: =IF(L4<>0,(O4/(L4+U4)),"0") -> 0.72532164 | R4: =+L4-O4 -> 1914083 | S4: =IF(L4<>0,(R4/(L4+U4)),"0") -> 0.26473331 | U4: =+Risultati!F3-(Risultati!G3+Risultati!H3) -> 71905 | V4: =IF(L4<>0,(U4/(L4+U4)),"0") -> 0.0099450488 | X4: =+U4+R4 -> 1985988 | Y4: =IF(L4<>0,(X4/(L4+U4)),"0") -> 0.27467836 | AA4: =+Risultati!K3 -> 657621 | AB4: =IF(L4<>0,(AA4/(L4+U4)),"0") -> 0.090954355 | AD4: =+Risultati!L3 -> 673251 | AE4: =IF(L4<>0,(AD4/(L4+U4)),"0") -> 0.093116112 | AG4: =+Risultati!M3+Risultati!P3+Risultati!Q3 -> 49284 | AH4: =IF(L4<>0,(AG4/(L4+U4)),"0") -> 0.0068163797 | AJ4: =+X4-AA4-AD4-AG4 -> 605832 | AK4: =IF(L4<>0,(AJ4/(L4+U4)),"0") -> 0.083791514 | AM4: =+Risultati!N3 -> 84069 | AN4: =IF(L4<>0,(AM4/(L4+U4)),"0") -> 0.011627429 | AP4: =+AJ4-AM4 -> 521763 | AQ4: =IF(L4<>0,(AP4/(L4+U4)),"0") -> 0.072164084 | AS4: =+Risultati!O3 -> 226867 | AT4: =IF(L4<>0,(AS4/(L4+U4)),"0") -> 0.031377559 | AV4: =+AP4-AS4 -> 294896 | AW4: =IF(L4<>0,(AV4/(L4+U4)),"0") -> 0.040786525 | AY4: =+Risultati!R3+Risultati!S3 -> -23511 | AZ4: =IF(L4<>0,(AY4/(L4+U4)),"0") -> -0.0032517633 | BB4: =+Risultati!T3 -> 0 | BC4: =IF(L4<>0,(BB4/(L4+U4)),"0") -> 0 | BE4: =+Risultati!U3 -> 77452 | BF4: =IF(L4<>0,(BE4/(L4+U4)),"0") -> 0.010712244 | BH4: =+AV4+AY4+BB4-BE4 -> 193933 | BI4: =IF(L4<>0,(+BH4/(L4+U4)),"0") -> 0.026822518 | BK4: =IF(ISNUMBER(Risultati!X3/100),(Risultati!X3/100)) -> 0.0704756 | BL4: =IF(ISNUMBER(Risultati!Y3/100),(Risultati!Y3/100)) -> 0.21644515 | BM4: =IF(ISNUMBER(Risultati!Z3/100),(Risultati!Z3/100)) -> 0.38929638 | BN4: =IF(AND(Risultati!AY3<0,calcoli!AP4<0),-IF(ISNUMBER(Risultati!AA3/100),(Risultati!AA3/100)),IF(ISNUMBER(Risultati!AA3/100),(Risultati!AA3/100))) -> 0.37408386 | BO4: =+BI4 -> 0.026822518 | BP4: =IF(Risultati!AB3>0,(AV4/Risultati!AB3),"0") -> 0.077344841 | BQ4: =IF(Risultati!AG3<>0,(BH4/Risultati!AG3),"0") -> 0.10191321 | BR4: =+BI4 -> 0.026822518 | BS4: =IF(Risultati!AB3>0,(Risultati!G3/Risultati!AB3),"0") -> 1.877474 | BT4: =IF(Risultati!AG3<>0,(Risultati!AB3/Risultati!AG3),"0") -> 2.0036244 | BU4: =IF(AND(Risultati!G3>0,(Risultati!AE3-Risultati!AF3)>=0),((Risultati!AE3-Risultati!AF3)/Risultati!G3*360),"0") -> 22.715981 | BV4: =IF(OR(E4="abbreviato",Risultati!G3=0),"0",((Risultati!AC3+Risultati!AD3)/Risultati!G3*360)) -> 0.13950748 | BW4: =IF(OR(E4="abbreviato",Risultati!G3=0,SUM(Risultati!I3+Risultati!K3+Risultati!M3)=0),"0",(((Risultati!AH3+Risultati!AI3)/(Risultati!I3+Risultati!K3+Risultati!N3)*360))) -> 60.192601 | BX4: =IF(Risultati!AB3>0,(+Risultati!AG3/Risultati!AB3),"0") -> 0.49909553 | BY4: =IF(OR(E4="abbreviato",Risultati!G3=0),"0",(((Risultati!AK3-(Risultati!AL3+Risultati!AM3))/Risultati!G3))) -> 0.05191535 | BZ4: =IF(Risultati!G3>0,(Risultati!AJ3/Risultati!G3),"0") -> 0.20018605 | CB4: =+Risultati!AP3 -> 0 | CC4: =IF($CX4>0,(CB4/$CX4),"0") -> 0 | CD4: =+Risultati!AQ3 -> 111652 | CE4: =IF($CX4>0,(CD4/$CX4),"0") -> 0.029283904 | CF4: =+Risultati!AR3 -> 2747980 | CG4: =IF($CX4>0,(CF4/$CX4),"0") -> 0.7207357 | CH4: =+Risultati!AS3 -> 8537 | CI4: =IF($CX4>0,(CH4/$CX4),"0") -> 0.0022390704 | CJ4: =+CH4+CF4+CD4 -> 2868169 | CK4: =IF($CX4>0,(CJ4/$CX4),"0") -> 0.75225868 | CL4: =+Risultati!AE3+Risultati!AF3 -> 459478 | CM4: =IF($CX4>0,(CL4/$CX4),"0") -> 0.12051114 | CN4: =+Risultati!AT3 -> 182206 | CO4: =IF($CX4>0,(CN4/$CX4),"0") -> 0.047788692 | CP4: =+Risultati!AU3 -> 212878 | CQ4: =IF($CX4>0,(CP4/$CX4),"0") -> 0.055833294 | CR4: =+Risultati!AL3 -> 72756 | CS4: =IF($CX4>0,(CR4/$CX4),"0") -> 0.019082325 | CT4: =+CR4+CP4+CN4+CL4 -> 927318 | CU4: =IF($CX4>0,(CT4/$CX4),"0") -> 0.24321545 | CV4: =+Risultati!AX3 -> 17256 | CW4: =IF($CX4>0,(CV4/$CX4),"0") -> 0.0045258755 | CX4: =+CV4+CT4+CJ4 -> 3812743 | CY4: =IF($CX4>0,(CX4/$CX4),"0") -> 1 | CZ4: =+Risultati!AG3 -> 1902923 | DA4: =IF($CX4>0,(CZ4/$CX4),"0") -> 0.49909553 | DB4: =+DL4-CZ4-DD4-DJ4 -> 89287 | DC4: =IF($CX4>0,(DB4/$CX4),"0") -> 0.023418048 | DD4: =+Risultati!AV3 -> 1799919 | DE4: =IF($CX4>0,(DD4/$CX4),"0") -> 0.47207981 | DF4: =+Risultati!AJ3 -> 1432997 | DG4: =IF($CX4>0,(DF4/$CX4),"0") -> 0.37584411 | DH4: =+DD4-DF4 -> 366922 | DI4: =IF($CX4>0,(DH4/$CX4),"0") -> 0.096235702 | DJ4: =+Risultati!AW3 -> 20614 | DK4: =IF($CX4>0,(DJ4/$CX4),"0") -> 0.0054066062 | DL4: =+CX4 -> 3812743 | DM4: =IF($CX4>0,(DL4/$CX4),"0") -> 1
B5: =+Risultati!B4 -> A.I.A. - AGRICOLA ITALIANA ALIMENTARE - S.P.A. | C5: =+Risultati!C4 -> 00233470236 | D5: =IF(YEAR(Risultati!D4)=1900,(MID(Risultati!$AP$1,29,4)),YEAR(Risultati!D4)) -> 2023 | E5: =+Risultati!E4 -> Dettagliato | F5: =(LEFT(Risultati!AN4,2)&"-")&VLOOKUP((LEFT(Risultati!AN4,2)),ateco!$B$4:$C$93,2,FALSE) -> 46-Commercio all'ingrosso (escluso quello di autoveicoli e di motocicli) | G5: =SUBSTITUTE((Risultati!AN4&"-"&Risultati!AO4),",",";") -> 463210-Commercio all'ingrosso di carne fresca; congelata e surgelata | I5: =+Risultati!G4 -> 4712306 | J5: =IF(L5<>0,(I5/L5),"0") -> 0.99990664 | L5: =+Risultati!G4+Risultati!H4 -> 4712746 | M5: =IF(L5<>0,(L5/(L5+U5)),"0") -> 0.97883074 | O5: =+Risultati!I4+Risultati!J4 -> 4095391 | P5: =IF(L5<>0,(O5/(L5+U5)),"0") -> 0.85060697 | R5: =+L5-O5 -> 617355 | S5: =IF(L5<>0,(R5/(L5+U5)),"0") -> 0.12822377 | U5: =+Risultati!F4-(Risultati!G4+Risultati!H4) -> 101923 | V5: =IF(L5<>0,(U5/(L5+U5)),"0") -> 0.021169264 | X5: =+U5+R5 -> 719278 | Y5: =IF(L5<>0,(X5/(L5+U5)),"0") -> 0.14939303 | AA5: =+Risultati!K4 -> 442257 | AB5: =IF(L5<>0,(AA5/(L5+U5)),"0") -> 0.091856159 | AD5: =+Risultati!L4 -> 57265 | AE5: =IF(L5<>0,(AD5/(L5+U5)),"0") -> 0.01189386 | AG5: =+Risultati!M4+Risultati!P4+Risultati!Q4 -> 13255 | AH5: =IF(L5<>0,(AG5/(L5+U5)),"0") -> 0.0027530449 | AJ5: =+X5-AA5-AD5-AG5 -> 206501 | AK5: =IF(L5<>0,(AJ5/(L5+U5)),"0") -> 0.042889968 | AM5: =+Risultati!N4 -> 5091 | AN5: =IF(L5<>0,(AM5/(L5+U5)),"0") -> 0.0010573936 | AP5: =+AJ5-AM5 -> 201410 | AQ5: =IF(L5<>0,(AP5/(L5+U5)),"0") -> 0.041832575 | AS5: =+Risultati!O4 -> 94636 | AT5: =IF(L5<>0,(AS5/(L5+U5)),"0") -> 0.019655764 | AV5: =+AP5-AS5 -> 106774 | AW5: =IF(L5<>0,(AV5/(L5+U5)),"0") -> 0.02217681 | AY5: =+Risultati!R4+Risultati!S4 -> -17934 | AZ5: =IF(L5<>0,(AY5/(L5+U5)),"0") -> -0.0037248667 | BB5: =+Risultati!T4 -> 0 | BC5: =IF(L5<>0,(BB5/(L5+U5)),"0") -> 0 | BE5: =+Risultati!U4 -> 21355 | BF5: =IF(L5<>0,(BE5/(L5+U5)),"0") -> 0.0044354036 | BH5: =+AV5+AY5+BB5-BE5 -> 67485 | BI5: =IF(L5<>0,(+BH5/(L5+U5)),"0") -> 0.01401654 | BK5: =IF(ISNUMBER(Risultati!X4/100),(Risultati!X4/100)) -> 0.11802779 | BL5: =IF(ISNUMBER(Risultati!Y4/100),(Risultati!Y4/100)) -> 0.24983947 | BM5: =IF(ISNUMBER(Risultati!Z4/100),(Risultati!Z4/100)) -> 0.36766654 | BN5: =IF(AND(Risultati!AY4<0,calcoli!AP5<0),-IF(ISNUMBER(Risultati!AA4/100),(Risultati!AA4/100)),IF(ISNUMBER(Risultati!AA4/100),(Risultati!AA4/100))) -> 0.60629406 | BO5: =+BI5 -> 0.01401654 | BP5: =IF(Risultati!AB4>0,(AV5/Risultati!AB4),"0") -> 0.067714081 | BQ5: =IF(Risultati!AG4<>0,(BH5/Risultati!AG4),"0") -> 0.14182944 | BR5: =+BI5 -> 0.01401654 | BS5: =IF(Risultati!AB4>0,(Risultati!G4/Risultati!AB4),"0") -> 2.9884566 | BT5: =IF(Risultati!AG4<>0,(Risultati!AB4/Risultati!AG4),"0") -> 3.3139478 | BU5: =IF(AND(Risultati!G4>0,(Risultati!AE4-Risultati!AF4)>=0),((Risultati!AE4-Risultati!AF4)/Risultati!G4*360),"0") -> 2.1181477 | BV5: =IF(OR(E5="abbreviato",Risultati!G4=0),"0",((Risultati!AC4+Risultati!AD4)/Risultati!G4*360)) -> 30.349345 | BW5: =IF(OR(E5="abbreviato",Risultati!G4=0,SUM(Risultati!I4+Risultati!K4+Risultati!M4)=0),"0",(((Risultati!AH4+Risultati!AI4)/(Risultati!I4+Risultati!K4+Risultati!N4)*360))) -> 29.022728 | BX5: =IF(Risultati!AB4>0,(+Risultati!AG4/Risultati!AB4),"0") -> 0.30175491 | BY5: =IF(OR(E5="abbreviato",Risultati!G4=0),"0",(((Risultati!AK4-(Risultati!AL4+Risultati!AM4))/Risultati!G4))) -> 0.12010595 | BZ5: =IF(Risultati!G4>0,(Risultati!AJ4/Risultati!G4),"0") -> 0.17512212 | CB5: =+Risultati!AP4 -> 0 | CC5: =IF($CX5>0,(CB5/$CX5),"0") -> 0 | CD5: =+Risultati!AQ4 -> 150 | CE5: =IF($CX5>0,(CD5/$CX5),"0") -> 9.5127264e-05 | CF5: =+Risultati!AR4 -> 523919 | CG5: =IF($CX5>0,(CF5/$CX5),"0") -> 0.33225988 | CH5: =+Risultati!AS4 -> 275760 | CI5: =IF($CX5>0,(CH5/$CX5),"0") -> 0.17488196 | CJ5: =+CH5+CF5+CD5 -> 799829 | CK5: =IF($CX5>0,(CJ5/$CX5),"0") -> 0.50723697 | CL5: =+Risultati!AE4+Risultati!AF4 -> 27726 | CM5: =IF($CX5>0,(CL5/$CX5),"0") -> 0.017583324 | CN5: =+Risultati!AT4 -> 585927 | CO5: =IF($CX5>0,(CN5/$CX5),"0") -> 0.37158422 | CP5: =+Risultati!AU4 -> 111758 | CQ5: =IF($CX5>0,(CP5/$CX5),"0") -> 0.070874885 | CR5: =+Risultati!AL4 -> 49282 | CS5: =IF($CX5>0,(CR5/$CX5),"0") -> 0.031253746 | CT5: =+CR5+CP5+CN5+CL5 -> 774693 | CU5: =IF($CX5>0,(CT5/$CX5),"0") -> 0.49129617 | CV5: =+Risultati!AX4 -> 2313 | CW5: =IF($CX5>0,(CV5/$CX5),"0") -> 0.0014668624 | CX5: =+CV5+CT5+CJ5 -> 1576835 | CY5: =IF($CX5>0,(CX5/$CX5),"0") -> 1 | CZ5: =+Risultati!AG4 -> 475818 | DA5: =IF($CX5>0,(CZ5/$CX5),"0") -> 0.3017551 | DB5: =+DL5-CZ5-DD5-DJ5 -> 28474 | DC5: =IF($CX5>0,(DB5/$CX5),"0") -> 0.018057692 | DD5: =+Risultati!AV4 -> 1068841 | DE5: =IF($CX5>0,(DD5/$CX5),"0") -> 0.67783947 | DF5: =+Risultati!AJ4 -> 825229 | DG5: =IF($CX5>0,(DF5/$CX5),"0") -> 0.52334518 | DH5: =+DD5-DF5 -> 243612 | DI5: =IF($CX5>0,(DH5/$CX5),"0") -> 0.15449429 | DJ5: =+Risultati!AW4 -> 3702 | DK5: =IF($CX5>0,(DJ5/$CX5),"0") -> 0.0023477409 | DL5: =+CX5 -> 1576835 | DM5: =IF($CX5>0,(DL5/$CX5),"0") -> 1
B6: =+Risultati!B5 -> PAC 2000 A SOCIETA' COOPERATIVA | C6: =+Risultati!C5 -> 00163040546 | D6: =IF(YEAR(Risultati!D5)=1900,(MID(Risultati!$AP$1,29,4)),YEAR(Risultati!D5)) -> 2023 | E6: =+Risultati!E5 -> Dettagliato | F6: =(LEFT(Risultati!AN5,2)&"-")&VLOOKUP((LEFT(Risultati!AN5,2)),ateco!$B$4:$C$93,2,FALSE) -> 46-Commercio all'ingrosso (escluso quello di autoveicoli e di motocicli) | G6: =SUBSTITUTE((Risultati!AN5&"-"&Risultati!AO5),",",";") -> 463890-Commercio all'ingrosso di altri prodotti alimentari | I6: =+Risultati!G5 -> 3939071 | J6: =IF(L6<>0,(I6/L6),"0") -> 1 | L6: =+Risultati!G5+Risultati!H5 -> 3939071 | M6: =IF(L6<>0,(L6/(L6+U6)),"0") -> 0.86802644 | O6: =+Risultati!I5+Risultati!J5 -> 4026552 | P6: =IF(L6<>0,(O6/(L6+U6)),"0") -> 0.88730404 | R6: =+L6-O6 -> -87481 | S6: =IF(L6<>0,(R6/(L6+U6)),"0") -> -0.019277596 | U6: =+Risultati!F5-(Risultati!G5+Risultati!H5) -> 598891 | V6: =IF(L6<>0,(U6/(L6+U6)),"0") -> 0.13197356 | X6: =+U6+R6 -> 511410 | Y6: =IF(L6<>0,(X6/(L6+U6)),"0") -> 0.11269596 | AA6: =+Risultati!K5 -> 337244 | AB6: =IF(L6<>0,(AA6/(L6+U6)),"0") -> 0.07431618 | AD6: =+Risultati!L5 -> 40571 | AE6: =IF(L6<>0,(AD6/(L6+U6)),"0") -> 0.0089403569 | AG6: =+Risultati!M5+Risultati!P5+Risultati!Q5 -> 26759 | AH6: =IF(L6<>0,(AG6/(L6+U6)),"0") -> 0.0058966999 | AJ6: =+X6-AA6-AD6-AG6 -> 106836 | AK6: =IF(L6<>0,(AJ6/(L6+U6)),"0") -> 0.023542727 | AM6: =+Risultati!N5 -> 31947 | AN6: =IF(L6<>0,(AM6/(L6+U6)),"0") -> 0.0070399444 | AP6: =+AJ6-AM6 -> 74889 | AQ6: =IF(L6<>0,(AP6/(L6+U6)),"0") -> 0.016502783 | AS6: =+Risultati!O5 -> 35158 | AT6: =IF(L6<>0,(AS6/(L6+U6)),"0") -> 0.0077475307 | AV6: =+AP6-AS6 -> 39731 | AW6: =IF(L6<>0,(AV6/(L6+U6)),"0") -> 0.0087552518 | AY6: =+Risultati!R5+Risultati!S5 -> 10320 | AZ6: =IF(L6<>0,(AY6/(L6+U6)),"0") -> 0.0022741486 | BB6: =+Risultati!T5 -> 0 | BC6: =IF(L6<>0,(BB6/(L6+U6)),"0") -> 0 | BE6: =+Risultati!U5 -> 7868 | BF6: =IF(L6<>0,(BE6/(L6+U6)),"0") -> 0.001733818 | BH6: =+AV6+AY6+BB6-BE6 -> 42183 | BI6: =IF(L6<>0,(+BH6/(L6+U6)),"0") -> 0.0092955825 | BK6: =IF(ISNUMBER(Risultati!X5/100),(Risultati!X5/100)) -> 0.09467291 | BL6: =IF(ISNUMBER(Risultati!Y5/100),(Risultati!Y5/100)) -> 0.17621953 | BM6: =IF(ISNUMBER(Risultati!Z5/100),(Risultati!Z5/100)) -> 0.63940179 | BN6: =IF(AND(Risultati!AY5<0,calcoli!AP6<0),-IF(ISNUMBER(Risultati!AA5/100),(Risultati!AA5/100)),IF(ISNUMBER(Risultati!AA5/100),(Risultati!AA5/100))) -> 0.18448107 | BO6: =+BI6 -> 0.0092955825 | BP6: =IF(Risultati!AB5>0,(AV6/Risultati!AB5),"0") -> 0.024285081 | BQ6: =IF(Risultati!AG5<>0,(BH6/Risultati!AG5),"0") -> 0.053797779 | BR6: =+BI6 -> 0.0092955825 | BS6: =IF(Risultati!AB5>0,(Risultati!G5/Risultati!AB5),"0") -> 2.4077083 | BT6: =IF(Risultati!AG5<>0,(Risultati!AB5/Risultati!AG5),"0") -> 2.0864925 | BU6: =IF(AND(Risultati!G5>0,(Risultati!AE5-Risultati!AF5)>=0),((Risultati!AE5-Risultati!AF5)/Risultati!G5*360),"0") -> 14.626667 | BV6: =IF(OR(E6="abbreviato",Risultati!G5=0),"0",((Risultati!AC5+Risultati!AD5)/Risultati!G5*360)) -> 25.33508 | BW6: =IF(OR(E6="abbreviato",Risultati!G5=0,SUM(Risultati!I5+Risultati!K5+Risultati!M5)=0),"0",(((Risultati!AH5+Risultati!AI5)/(Risultati!I5+Risultati!K5+Risultati!N5)*360))) -> 57.586209 | BX6: =IF(Risultati!AB5>0,(+Risultati!AG5/Risultati!AB5),"0") -> 0.47927324 | BY6: =IF(OR(E6="abbreviato",Risultati!G5=0),"0",(((Risultati!AK5-(Risultati!AL5+Risultati!AM5))/Risultati!G5))) -> -0.010046024 | BZ6: =IF(Risultati!G5>0,(Risultati!AJ5/Risultati!G5),"0") -> 0.1991731 | CB6: =+Risultati!AP5 -> 3026 | CC6: =IF($CX6>0,(CB6/$CX6),"0") -> 0.0018530324 | CD6: =+Risultati!AQ5 -> 37853 | CE6: =IF($CX6>0,(CD6/$CX6),"0") -> 0.023180051 | CF6: =+Risultati!AR5 -> 365022 | CG6: =IF($CX6>0,(CF6/$CX6),"0") -> 0.22352861 | CH6: =+Risultati!AS5 -> 386597 | CI6: =IF($CX6>0,(CH6/$CX6),"0") -> 0.2367405 | CJ6: =+CH6+CF6+CD6 -> 789472 | CK6: =IF($CX6>0,(CJ6/$CX6),"0") -> 0.48344916 | CL6: =+Risultati!AE5+Risultati!AF5 -> 160043 | CM6: =IF($CX6>0,(CL6/$CX6),"0") -> 0.098005571 | CN6: =+Risultati!AT5 -> 540065 | CO6: =IF($CX6>0,(CN6/$CX6),"0") -> 0.33071974 | CP6: =+Risultati!AU5 -> 50083 | CQ6: =IF($CX6>0,(CP6/$CX6),"0") -> 0.030669339 | CR6: =+Risultati!AL5 -> 87591 | CS6: =IF($CX6>0,(CR6/$CX6),"0") -> 0.053638122 | CT6: =+CR6+CP6+CN6+CL6 -> 837782 | CU6: =IF($CX6>0,(CT6/$CX6),"0") -> 0.51303277 | CV6: =+Risultati!AX5 -> 5745 | CW6: =IF($CX6>0,(CV6/$CX6),"0") -> 0.0035180671 | CX6: =+CV6+CT6+CJ6 -> 1632999 | CY6: =IF($CX6>0,(CX6/$CX6),"0") -> 1 | CZ6: =+Risultati!AG5 -> 784103 | DA6: =IF($CX6>0,(CZ6/$CX6),"0") -> 0.48016135 | DB6: =+DL6-CZ6-DD6-DJ6 -> 28392 | DC6: =IF($CX6>0,(DB6/$CX6),"0") -> 0.017386416 | DD6: =+Risultati!AV5 -> 815565 | DE6: =IF($CX6>0,(DD6/$CX6),"0") -> 0.49942774 | DF6: =+Risultati!AJ5 -> 784557 | DG6: =IF($CX6>0,(DF6/$CX6),"0") -> 0.48043936 | DH6: =+DD6-DF6 -> 31008 | DI6: =IF($CX6>0,(DH6/$CX6),"0") -> 0.018988377 | DJ6: =+Risultati!AW5 -> 4939 | DK6: =IF($CX6>0,(DJ6/$CX6),"0") -> 0.0030244966 | DL6: =+CX6 -> 1632999 | DM6: =IF($CX6>0,(DL6/$CX6),"0") -> 1
B7: =+Risultati!B6 -> COOP ALLEANZA 3.0 SOCIETA' COOPERATIVA | C7: =+Risultati!C6 -> 03503411203 | D7: =IF(YEAR(Risultati!D6)=1900,(MID(Risultati!$AP$1,29,4)),YEAR(Risultati!D6)) -> 2023 | E7: =+Risultati!E6 -> Dettagliato | F7: =(LEFT(Risultati!AN6,2)&"-")&VLOOKUP((LEFT(Risultati!AN6,2)),ateco!$B$4:$C$93,2,FALSE) -> 47-Commercio al dettaglio (escluso quello di autoveicoli e di motocicli) | G7: =SUBSTITUTE((Risultati!AN6&"-"&Risultati!AO6),",",";") -> 471120-Supermercati | I7: =+Risultati!G6 -> 3895925 | J7: =IF(L7<>0,(I7/L7),"0") -> 1.0052921 | L7: =+Risultati!G6+Risultati!H6 -> 3875416 | M7: =IF(L7<>0,(L7/(L7+U7)),"0") -> 0.88622605 | O7: =+Risultati!I6+Risultati!J6 -> 3012376 | P7: =IF(L7<>0,(O7/(L7+U7)),"0") -> 0.68886697 | R7: =+L7-O7 -> 863040 | S7: =IF(L7<>0,(R7/(L7+U7)),"0") -> 0.19735908 | U7: =+Risultati!F6-(Risultati!G6+Risultati!H6) -> 497527 | V7: =IF(L7<>0,(U7/(L7+U7)),"0") -> 0.11377395 | X7: =+U7+R7 -> 1360567 | Y7: =IF(L7<>0,(X7/(L7+U7)),"0") -> 0.31113303 | AA7: =+Risultati!K6 -> 462223 | AB7: =IF(L7<>0,(AA7/(L7+U7)),"0") -> 0.10570067 | AD7: =+Risultati!L6 -> 596887 | AE7: =IF(L7<>0,(AD7/(L7+U7)),"0") -> 0.13649549 | AG7: =+Risultati!M6+Risultati!P6+Risultati!Q6 -> 90262 | AH7: =IF(L7<>0,(AG7/(L7+U7)),"0") -> 0.020641019 | AJ7: =+X7-AA7-AD7-AG7 -> 211195 | AK7: =IF(L7<>0,(AJ7/(L7+U7)),"0") -> 0.04829585 | AM7: =+Risultati!N6 -> 145796 | AN7: =IF(L7<>0,(AM7/(L7+U7)),"0") -> 0.033340476 | AP7: =+AJ7-AM7 -> 65399 | AQ7: =IF(L7<>0,(AP7/(L7+U7)),"0") -> 0.014955374 | AS7: =+Risultati!O6 -> 106806 | AT7: =IF(L7<>0,(AS7/(L7+U7)),"0") -> 0.024424284 | AV7: =+AP7-AS7 -> -41407 | AW7: =IF(L7<>0,(AV7/(L7+U7)),"0") -> -0.0094689092 | AY7: =+Risultati!R6+Risultati!S6 -> 76352 | AZ7: =IF(L7<>0,(AY7/(L7+U7)),"0") -> 0.017460095 | BB7: =+Risultati!T6 -> 0 | BC7: =IF(L7<>0,(BB7/(L7+U7)),"0") -> 0 | BE7: =+Risultati!U6 -> 14932 | BF7: =IF(L7<>0,(BE7/(L7+U7)),"0") -> 0.003414634 | BH7: =+AV7+AY7+BB7-BE7 -> 20013 | BI7: =IF(L7<>0,(+BH7/(L7+U7)),"0") -> 0.0045765518 | BK7: =IF(ISNUMBER(Risultati!X6/100),(Risultati!X6/100)) -> 0.017454805 | BL7: =IF(ISNUMBER(Risultati!Y6/100),(Risultati!Y6/100)) -> -0.038114223 | BM7: =IF(ISNUMBER(Risultati!Z6/100),(Risultati!Z6/100)) -> 0.067572385 | BN7: =IF(AND(Risultati!AY6<0,calcoli!AP7<0),-IF(ISNUMBER(Risultati!AA6/100),(Risultati!AA6/100)),IF(ISNUMBER(Risultati!AA6/100),(Risultati!AA6/100))) -> -1.4841824 | BO7: =+BI7 -> 0.0045765518 | BP7: =IF(Risultati!AB6>0,(AV7/Risultati!AB6),"0") -> -0.0066289404 | BQ7: =IF(Risultati!AG6<>0,(BH7/Risultati!AG6),"0") -> 0.012616906 | BR7: =+BI7 -> 0.0045765518 | BS7: =IF(Risultati!AB6>0,(Risultati!G6/Risultati!AB6),"0") -> 0.62370746 | BT7: =IF(Risultati!AG6<>0,(Risultati!AB6/Risultati!AG6),"0") -> 3.9379513 | BU7: =IF(AND(Risultati!G6>0,(Risultati!AE6-Risultati!AF6)>=0),((Risultati!AE6-Risultati!AF6)/Risultati!G6*360),"0") -> 45.20702 | BV7: =IF(OR(E7="abbreviato",Risultati!G6=0),"0",((Risultati!AC6+Risultati!AD6)/Risultati!G6*360)) -> 20.939541 | BW7: =IF(OR(E7="abbreviato",Risultati!G6=0,SUM(Risultati!I6+Risultati!K6+Risultati!M6)=0),"0",(((Risultati!AH6+Risultati!AI6)/(Risultati!I6+Risultati!K6+Risultati!N6)*360))) -> 69.6617 | BX7: =IF(Risultati!AB6>0,(+Risultati!AG6/Risultati!AB6),"0") -> 0.25393915 | BY7: =IF(OR(E7="abbreviato",Risultati!G6=0),"0",(((Risultati!AK6-(Risultati!AL6+Risultati!AM6))/Risultati!G6))) -> 0.85382829 | BZ7: =IF(Risultati!G6>0,(Risultati!AJ6/Risultati!G6),"0") -> 0.87980492 | CB7: =+Risultati!AP6 -> 0 | CC7: =IF($CX7>0,(CB7/$CX7),"0") -> 0 | CD7: =+Risultati!AQ6 -> 173036 | CE7: =IF($CX7>0,(CD7/$CX7),"0") -> 0.027701725 | CF7: =+Risultati!AR6 -> 1077666 | CG7: =IF($CX7>0,(CF7/$CX7),"0") -> 0.17252599 | CH7: =+Risultati!AS6 -> 2652270 | CI7: =IF($CX7>0,(CH7/$CX7),"0") -> 0.42460791 | CJ7: =+CH7+CF7+CD7 -> 3902972 | CK7: =IF($CX7>0,(CJ7/$CX7),"0") -> 0.62483563 | CL7: =+Risultati!AE6+Risultati!AF6 -> 489231 | CM7: =IF($CX7>0,(CL7/$CX7),"0") -> 0.078322099 | CN7: =+Risultati!AT6 -> 338663 | CO7: =IF($CX7>0,(CN7/$CX7),"0") -> 0.054217327 | CP7: =+Risultati!AU6 -> 1273876 | CQ7: =IF($CX7>0,(CP7/$CX7),"0") -> 0.20393769 | CR7: =+Risultati!AL6 -> 225861 | CS7: =IF($CX7>0,(CR7/$CX7),"0") -> 0.036158599 | CT7: =+CR7+CP7+CN7+CL7 -> 2327631 | CU7: =IF($CX7>0,(CT7/$CX7),"0") -> 0.37263572 | CV7: =+Risultati!AX6 -> 15795 | CW7: =IF($CX7>0,(CV7/$CX7),"0") -> 0.0025286573 | CX7: =+CV7+CT7+CJ7 -> 6246398 | CY7: =IF($CX7>0,(CX7/$CX7),"0") -> 1 | CZ7: =+Risultati!AG6 -> 1586205 | DA7: =IF($CX7>0,(CZ7/$CX7),"0") -> 0.25393915 | DB7: =+DL7-CZ7-DD7-DJ7 -> 181537 | DC7: =IF($CX7>0,(DB7/$CX7),"0") -> 0.029062669 | DD7: =+Risultati!AV6 -> 4475076 | DE7: =IF($CX7>0,(DD7/$CX7),"0") -> 0.71642505 | DF7: =+Risultati!AJ6 -> 3427654 | DG7: =IF($CX7>0,(DF7/$CX7),"0") -> 0.54874089 | DH7: =+DD7-DF7 -> 1047422 | DI7: =IF($CX7>0,(DH7/$CX7),"0") -> 0.16768416 | DJ7: =+Risultati!AW6 -> 3580 | DK7: =IF($CX7>0,(DJ7/$CX7),"0") -> 0.00057313031 | DL7: =+CX7 -> 6246398 | DM7: =IF($CX7>0,(DL7/$CX7),"0") -> 1
B8: =+Risultati!B7 -> GS SPA | C8: =+Risultati!C7 -> 12683790153 | D8: =IF(YEAR(Risultati!D7)=1900,(MID(Risultati!$AP$1,29,4)),YEAR(Risultati!D7)) -> 2023 | E8: =+Risultati!E7 -> Dettagliato | F8: =(LEFT(Risultati!AN7,2)&"-")&VLOOKUP((LEFT(Risultati!AN7,2)),ateco!$B$4:$C$93,2,FALSE) -> 47-Commercio al dettaglio (escluso quello di autoveicoli e di motocicli) | G8: =SUBSTITUTE((Risultati!AN7&"-"&Risultati!AO7),",",";") -> 471100-Commercio al dettaglio in esercizi non specializzati con prevalenza di prodotti alimentari e bevande | I8: =+Risultati!G7 -> 3836122 | J8: =IF(L8<>0,(I8/L8),"0") -> 1 | L8: =+Risultati!G7+Risultati!H7 -> 3836122 | M8: =IF(L8<>0,(L8/(L8+U8)),"0") -> 0.85591137 | O8: =+Risultati!I7+Risultati!J7 -> 3289029 | P8: =IF(L8<>0,(O8/(L8+U8)),"0") -> 0.73384457 | R8: =+L8-O8 -> 547093 | S8: =IF(L8<>0,(R8/(L8+U8)),"0") -> 0.1220668 | U8: =+Risultati!F7-(Risultati!G7+Risultati!H7) -> 645793 | V8: =IF(L8<>0,(U8/(L8+U8)),"0") -> 0.14408863 | X8: =+U8+R8 -> 1192886 | Y8: =IF(L8<>0,(X8/(L8+U8)),"0") -> 0.26615543 | AA8: =+Risultati!K7 -> 512822 | AB8: =IF(L8<>0,(AA8/(L8+U8)),"0") -> 0.11442029 | AD8: =+Risultati!L7 -> 484359 | AE8: =IF(L8<>0,(AD8/(L8+U8)),"0") -> 0.10806965 | AG8: =+Risultati!M7+Risultati!P7+Risultati!Q7 -> 23534 | AH8: =IF(L8<>0,(AG8/(L8+U8)),"0") -> 0.0052508805 | AJ8: =+X8-AA8-AD8-AG8 -> 172171 | AK8: =IF(L8<>0,(AJ8/(L8+U8)),"0") -> 0.038414606 | AM8: =+Risultati!N7 -> 201389 | AN8: =IF(L8<>0,(AM8/(L8+U8)),"0") -> 0.044933695 | AP8: =+AJ8-AM8 -> -29218 | AQ8: =IF(L8<>0,(AP8/(L8+U8)),"0") -> -0.0065190884 | AS8: =+Risultati!O7 -> 83298 | AT8: =IF(L8<>0,(AS8/(L8+U8)),"0") -> 0.018585359 | AV8: =+AP8-AS8 -> -112516 | AW8: =IF(L8<>0,(AV8/(L8+U8)),"0") -> -0.025104448 | AY8: =+Risultati!R7+Risultati!S7 -> -15793 | AZ8: =IF(L8<>0,(AY8/(L8+U8)),"0") -> -0.003523717 | BB8: =+Risultati!T7 -> 0 | BC8: =IF(L8<>0,(BB8/(L8+U8)),"0") -> 0 | BE8: =+Risultati!U7 -> 435 | BF8: =IF(L8<>0,(BE8/(L8+U8)),"0") -> 9.7056727e-05 | BH8: =+AV8+AY8+BB8-BE8 -> -128744 | BI8: =IF(L8<>0,(+BH8/(L8+U8)),"0") -> -0.028725221 | BK8: =IF(ISNUMBER(Risultati!X7/100),(Risultati!X7/100)) -> -0.0019279142 | BL8: =IF(ISNUMBER(Risultati!Y7/100),(Risultati!Y7/100)) -> -0.012921669 | BM8: =IF(ISNUMBER(Risultati!Z7/100),(Risultati!Z7/100)) -> 0.10353829 | BN8: =IF(AND(Risultati!AY7<0,calcoli!AP8<0),-IF(ISNUMBER(Risultati!AA7/100),(Risultati!AA7/100)),IF(ISNUMBER(Risultati!AA7/100),(Risultati!AA7/100))) -> -0.88887452 | BO8: =+BI8 -> -0.028725221 | BP8: =IF(Risultati!AB7>0,(AV8/Risultati!AB7),"0") -> -0.072670765 | BQ8: =IF(Risultati!AG7<>0,(BH8/Risultati!AG7),"0") -> -0.84500423 | BR8: =+BI8 -> -0.028725221 | BS8: =IF(Risultati!AB7>0,(Risultati!G7/Risultati!AB7),"0") -> 2.477638 | BT8: =IF(Risultati!AG7<>0,(Risultati!AB7/Risultati!AG7),"0") -> 10.16217 | BU8: =IF(AND(Risultati!G7>0,(Risultati!AE7-Risultati!AF7)>=0),((Risultati!AE7-Risultati!AF7)/Risultati!G7*360),"0") -> 34.407529 | BV8: =IF(OR(E8="abbreviato",Risultati!G7=0),"0",((Risultati!AC7+Risultati!AD7)/Risultati!G7*360)) -> 12.423546 | BW8: =IF(OR(E8="abbreviato",Risultati!G7=0,SUM(Risultati!I7+Risultati!K7+Risultati!M7)=0),"0",(((Risultati!AH7+Risultati!AI7)/(Risultati!I7+Risultati!K7+Risultati!N7)*360))) -> 67.331744 | BX8: =IF(Risultati!AB7>0,(+Risultati!AG7/Risultati!AB7),"0") -> 0.098404183 | BY8: =IF(OR(E8="abbreviato",Risultati!G7=0),"0",(((Risultati!AK7-(Risultati!AL7+Risultati!AM7))/Risultati!G7))) -> -0.0098925425 | BZ8: =IF(Risultati!G7>0,(Risultati!AJ7/Risultati!G7),"0") -> 0.33975223 | CB8: =+Risultati!AP7 -> 0 | CC8: =IF($CX8>0,(CB8/$CX8),"0") -> 0 | CD8: =+Risultati!AQ7 -> 242393 | CE8: =IF($CX8>0,(CD8/$CX8),"0") -> 0.15655429 | CF8: =+Risultati!AR7 -> 103985 | CG8: =IF($CX8>0,(CF8/$CX8),"0") -> 0.067160757 | CH8: =+Risultati!AS7 -> 340820 | CI8: =IF($CX8>0,(CH8/$CX8),"0") -> 0.2201253 | CJ8: =+CH8+CF8+CD8 -> 687198 | CK8: =IF($CX8>0,(CJ8/$CX8),"0") -> 0.44384034 | CL8: =+Risultati!AE7+Risultati!AF7 -> 366643 | CM8: =IF($CX8>0,(CL8/$CX8),"0") -> 0.23680359 | CN8: =+Risultati!AT7 -> 418326 | CO8: =IF($CX8>0,(CN8/$CX8),"0") -> 0.27018407 | CP8: =+Risultati!AU7 -> 0 | CQ8: =IF($CX8>0,(CP8/$CX8),"0") -> 0 | CR8: =+Risultati!AL7 -> 37962 | CS8: =IF($CX8>0,(CR8/$CX8),"0") -> 0.024518504 | CT8: =+CR8+CP8+CN8+CL8 -> 822931 | CU8: =IF($CX8>0,(CT8/$CX8),"0") -> 0.53150617 | CV8: =+Risultati!AX7 -> 38171 | CW8: =IF($CX8>0,(CV8/$CX8),"0") -> 0.024653491 | CX8: =+CV8+CT8+CJ8 -> 1548300 | CY8: =IF($CX8>0,(CX8/$CX8),"0") -> 1 | CZ8: =+Risultati!AG7 -> 152359 | DA8: =IF($CX8>0,(CZ8/$CX8),"0") -> 0.098404056 | DB8: =+DL8-CZ8-DD8-DJ8 -> 85461 | DC8: =IF($CX8>0,(DB8/$CX8),"0") -> 0.055196667 | DD8: =+Risultati!AV7 -> 1309071 | DE8: =IF($CX8>0,(DD8/$CX8),"0") -> 0.84548925 | DF8: =+Risultati!AJ7 -> 1303331 | DG8: =IF($CX8>0,(DF8/$CX8),"0") -> 0.84178195 | DH8: =+DD8-DF8 -> 5740 | DI8: =IF($CX8>0,(DH8/$CX8),"0") -> 0.0037072919 | DJ8: =+Risultati!AW7 -> 1409 | DK8: =IF($CX8>0,(DJ8/$CX8),"0") -> 0.00091003036 | DL8: =+CX8 -> 1548300 | DM8: =IF($CX8>0,(DL8/$CX8),"0") -> 1
B9: =+Risultati!B8 -> MD S.P.A. | C9: =+Risultati!C8 -> 03185210618 | D9: =IF(YEAR(Risultati!D8)=1900,(MID(Risultati!$AP$1,29,4)),YEAR(Risultati!D8)) -> 2023 | E9: =+Risultati!E8 -> Dettagliato | F9: =(LEFT(Risultati!AN8,2)&"-")&VLOOKUP((LEFT(Risultati!AN8,2)),ateco!$B$4:$C$93,2,FALSE) -> 47-Commercio al dettaglio (escluso quello di autoveicoli e di motocicli) | G9: =SUBSTITUTE((Risultati!AN8&"-"&Risultati!AO8),",",";") -> 471120-Supermercati | I9: =+Risultati!G8 -> 3591475 | J9: =IF(L9<>0,(I9/L9),"0") -> 1 | L9: =+Risultati!G8+Risultati!H8 -> 3591475 | M9: =IF(L9<>0,(L9/(L9+U9)),"0") -> 0.97377421 | O9: =+Risultati!I8+Risultati!J8 -> 2774484 | P9: =IF(L9<>0,(O9/(L9+U9)),"0") -> 0.75225943 | R9: =+L9-O9 -> 816991 | S9: =IF(L9<>0,(R9/(L9+U9)),"0") -> 0.22151477 | U9: =+Risultati!F8-(Risultati!G8+Risultati!H8) -> 96726 | V9: =IF(L9<>0,(U9/(L9+U9)),"0") -> 0.026225794 | X9: =+U9+R9 -> 913717 | Y9: =IF(L9<>0,(X9/(L9+U9)),"0") -> 0.24774057 | AA9: =+Risultati!K8 -> 309641 | AB9: =IF(L9<>0,(AA9/(L9+U9)),"0") -> 0.083954481 | AD9: =+Risultati!L8 -> 281347 | AE9: =IF(L9<>0,(AD9/(L9+U9)),"0") -> 0.07628299 | AG9: =+Risultati!M8+Risultati!P8+Risultati!Q8 -> 19495 | AH9: =IF(L9<>0,(AG9/(L9+U9)),"0") -> 0.0052857748 | AJ9: =+X9-AA9-AD9-AG9 -> 303234 | AK9: =IF(L9<>0,(AJ9/(L9+U9)),"0") -> 0.08221732 | AM9: =+Risultati!N8 -> 87258 | AN9: =IF(L9<>0,(AM9/(L9+U9)),"0") -> 0.023658689 | AP9: =+AJ9-AM9 -> 215976 | AQ9: =IF(L9<>0,(AP9/(L9+U9)),"0") -> 0.058558631 | AS9: =+Risultati!O8 -> 89695 | AT9: =IF(L9<>0,(AS9/(L9+U9)),"0") -> 0.024319445 | AV9: =+AP9-AS9 -> 126281 | AW9: =IF(L9<>0,(AV9/(L9+U9)),"0") -> 0.034239186 | AY9: =+Risultati!R8+Risultati!S8 -> -11047 | AZ9: =IF(L9<>0,(AY9/(L9+U9)),"0") -> -0.0029952272 | BB9: =+Risultati!T8 -> 0 | BC9: =IF(L9<>0,(BB9/(L9+U9)),"0") -> 0 | BE9: =+Risultati!U8 -> 34984 | BF9: =IF(L9<>0,(BE9/(L9+U9)),"0") -> 0.0094853833 | BH9: =+AV9+AY9+BB9-BE9 -> 80250 | BI9: =IF(L9<>0,(+BH9/(L9+U9)),"0") -> 0.021758576 | BK9: =IF(ISNUMBER(Risultati!X8/100),(Risultati!X8/100)) -> 0.077535384 | BL9: =IF(ISNUMBER(Risultati!Y8/100),(Risultati!Y8/100)) -> 0.19540189 | BM9: =IF(ISNUMBER(Risultati!Z8/100),(Risultati!Z8/100)) -> 0.44543083 | BN9: =IF(AND(Risultati!AY8<0,calcoli!AP9<0),-IF(ISNUMBER(Risultati!AA8/100),(Risultati!AA8/100)),IF(ISNUMBER(Risultati!AA8/100),(Risultati!AA8/100))) -> 0.58204473 | BO9: =+BI9 -> 0.021758576 | BP9: =IF(Risultati!AB8>0,(AV9/Risultati!AB8),"0") -> 0.072482352 | BQ9: =IF(Risultati!AG8<>0,(BH9/Risultati!AG8),"0") -> 0.13829936 | BR9: =+BI9 -> 0.021758576 | BS9: =IF(Risultati!AB8>0,(Risultati!G8/Risultati!AB8),"0") -> 2.061423 | BT9: =IF(Risultati!AG8<>0,(Risultati!AB8/Risultati!AG8),"0") -> 3.0024851 | BU9: =IF(AND(Risultati!G8>0,(Risultati!AE8-Risultati!AF8)>=0),((Risultati!AE8-Risultati!AF8)/Risultati!G8*360),"0") -> 18.788492 | BV9: =IF(OR(E9="abbreviato",Risultati!G8=0),"0",((Risultati!AC8+Risultati!AD8)/Risultati!G8*360)) -> 12.82056 | BW9: =IF(OR(E9="abbreviato",Risultati!G8=0,SUM(Risultati!I8+Risultati!K8+Risultati!M8)=0),"0",(((Risultati!AH8+Risultati!AI8)/(Risultati!I8+Risultati!K8+Risultati!N8)*360))) -> 80.969873 | BX9: =IF(Risultati!AB8>0,(+Risultati!AG8/Risultati!AB8),"0") -> 0.33305744 | BY9: =IF(OR(E9="abbreviato",Risultati!G8=0),"0",(((Risultati!AK8-(Risultati!AL8+Risultati!AM8))/Risultati!G8))) -> 0.035122338 | BZ9: =IF(Risultati!G8>0,(Risultati!AJ8/Risultati!G8),"0") -> 0.26932945 | CB9: =+Risultati!AP8 -> 0 | CC9: =IF($CX9>0,(CB9/$CX9),"0") -> 0 | CD9: =+Risultati!AQ8 -> 377888 | CE9: =IF($CX9>0,(CD9/$CX9),"0") -> 0.21689891 | CF9: =+Risultati!AR8 -> 607643 | CG9: =IF($CX9>0,(CF9/$CX9),"0") -> 0.34877292 | CH9: =+Risultati!AS8 -> 186865 | CI9: =IF($CX9>0,(CH9/$CX9),"0") -> 0.10725616 | CJ9: =+CH9+CF9+CD9 -> 1172396 | CK9: =IF($CX9>0,(CJ9/$CX9),"0") -> 0.67292799 | CL9: =+Risultati!AE8+Risultati!AF8 -> 187440 | CM9: =IF($CX9>0,(CL9/$CX9),"0") -> 0.10758619 | CN9: =+Risultati!AT8 -> 173715 | CO9: =IF($CX9>0,(CN9/$CX9),"0") -> 0.099708362 | CP9: =+Risultati!AU8 -> 0 | CQ9: =IF($CX9>0,(CP9/$CX9),"0") -> 0 | CR9: =+Risultati!AL8 -> 195835 | CS9: =IF($CX9>0,(CR9/$CX9),"0") -> 0.11240473 | CT9: =+CR9+CP9+CN9+CL9 -> 556990 | CU9: =IF($CX9>0,(CT9/$CX9),"0") -> 0.31969928 | CV9: =+Risultati!AX8 -> 12845 | CW9: =IF($CX9>0,(CV9/$CX9),"0") -> 0.0073727307 | CX9: =+CV9+CT9+CJ9 -> 1742231 | CY9: =IF($CX9>0,(CX9/$CX9),"0") -> 1 | CZ9: =+Risultati!AG8 -> 580263 | DA9: =IF($CX9>0,(CZ9/$CX9),"0") -> 0.33305744 | DB9: =+DL9-CZ9-DD9-DJ9 -> 37136 | DC9: =IF($CX9>0,(DB9/$CX9),"0") -> 0.021315199 | DD9: =+Risultati!AV8 -> 1116038 | DE9: =IF($CX9>0,(DD9/$CX9),"0") -> 0.64057981 | DF9: =+Risultati!AJ8 -> 967290 | DG9: =IF($CX9>0,(DF9/$CX9),"0") -> 0.55520192 | DH9: =+DD9-DF9 -> 148748 | DI9: =IF($CX9>0,(DH9/$CX9),"0") -> 0.085377886 | DJ9: =+Risultati!AW8 -> 8794 | DK9: =IF($CX9>0,(DJ9/$CX9),"0") -> 0.0050475511 | DL9: =+CX9 -> 1742231 | DM9: =IF($CX9>0,(DL9/$CX9),"0") -> 1
B10: =+Risultati!B9 -> SPESA INTELLIGENTE S.P.A. | C10: =+Risultati!C9 -> 02416840235 | D10: =IF(YEAR(Risultati!D9)=1900,(MID(Risultati!$AP$1,29,4)),YEAR(Risultati!D9)) -> 2023 | E10: =+Risultati!E9 -> Dettagliato | F10: =(LEFT(Risultati!AN9,2)&"-")&VLOOKUP((LEFT(Risultati!AN9,2)),ateco!$B$4:$C$93,2,FALSE) -> 47-Commercio al dettaglio (escluso quello di autoveicoli e di motocicli) | G10: =SUBSTITUTE((Risultati!AN9&"-"&Risultati!AO9),",",";") -> 471100-Commercio al dettaglio in esercizi non specializzati con prevalenza di prodotti alimentari e bevande | I10: =+Risultati!G9 -> 3162613 | J10: =IF(L10<>0,(I10/L10),"0") -> 1 | L10: =+Risultati!G9+Risultati!H9 -> 3162613 | M10: =IF(L10<>0,(L10/(L10+U10)),"0") -> 0.99405224 | O10: =+Risultati!I9+Risultati!J9 -> 2480435 | P10: =IF(L10<>0,(O10/(L10+U10)),"0") -> 0.77963443 | R10: =+L10-O10 -> 682178 | S10: =IF(L10<>0,(R10/(L10+U10)),"0") -> 0.21441782 | U10: =+Risultati!F9-(Risultati!G9+Risultati!H9) -> 18923 | V10: =IF(L10<>0,(U10/(L10+U10)),"0") -> 0.0059477561 | X10: =+U10+R10 -> 701101 | Y10: =IF(L10<>0,(X10/(L10+U10)),"0") -> 0.22036557 | AA10: =+Risultati!K9 -> 212848 | AB10: =IF(L10<>0,(AA10/(L10+U10)),"0") -> 0.066901019 | AD10: =+Risultati!L9 -> 225039 | AE10: =IF(L10<>0,(AD10/(L10+U10)),"0") -> 0.070732816 | AG10: =+Risultati!M9+Risultati!P9+Risultati!Q9 -> 11545 | AH10: =IF(L10<>0,(AG10/(L10+U10)),"0") -> 0.0036287504 | AJ10: =+X10-AA10-AD10-AG10 -> 251669 | AK10: =IF(L10<>0,(AJ10/(L10+U10)),"0") -> 0.079102987 | AM10: =+Risultati!N9 -> 13125 | AN10: =IF(L10<>0,(AM10/(L10+U10)),"0") -> 0.0041253659 | AP10: =+AJ10-AM10 -> 238544 | AQ10: =IF(L10<>0,(AP10/(L10+U10)),"0") -> 0.074977621 | AS10: =+Risultati!O9 -> 67213 | AT10: =IF(L10<>0,(AS10/(L10+U10)),"0") -> 0.021125959 | AV10: =+AP10-AS10 -> 171331 | AW10: =IF(L10<>0,(AV10/(L10+U10)),"0") -> 0.053851662 | AY10: =+Risultati!R9+Risultati!S9 -> 2678 | AZ10: =IF(L10<>0,(AY10/(L10+U10)),"0") -> 0.00084173179 | BB10: =+Risultati!T9 -> 0 | BC10: =IF(L10<>0,(BB10/(L10+U10)),"0") -> 0 | BE10: =+Risultati!U9 -> 45598 | BF10: =IF(L10<>0,(BE10/(L10+U10)),"0") -> 0.014332071 | BH10: =+AV10+AY10+BB10-BE10 -> 128411 | BI10: =IF(L10<>0,(+BH10/(L10+U10)),"0") -> 0.040361322 | BK10: =IF(ISNUMBER(Risultati!X9/100),(Risultati!X9/100)) -> 0.11617276 | BL10: =IF(ISNUMBER(Risultati!Y9/100),(Risultati!Y9/100)) -> 0.2684426 | BM10: =IF(ISNUMBER(Risultati!Z9/100),(Risultati!Z9/100)) -> 0.4769814 | BN10: =IF(AND(Risultati!AY9<0,calcoli!AP10<0),-IF(ISNUMBER(Risultati!AA9/100),(Risultati!AA9/100)),IF(ISNUMBER(Risultati!AA9/100),(Risultati!AA9/100))) -> 0.66959461 | BO10: =+BI10 -> 0.040361322 | BP10: =IF(Risultati!AB9>0,(AV10/Risultati!AB9),"0") -> 0.12606535 | BQ10: =IF(Risultati!AG9<>0,(BH10/Risultati!AG9),"0") -> 0.15568536 | BR10: =+BI10 -> 0.040361322 | BS10: =IF(Risultati!AB9>0,(Risultati!G9/Risultati!AB9),"0") -> 2.3270506 | BT10: =IF(Risultati!AG9<>0,(Risultati!AB9/Risultati!AG9),"0") -> 1.647729 | BU10: =IF(AND(Risultati!G9>0,(Risultati!AE9-Risultati!AF9)>=0),((Risultati!AE9-Risultati!AF9)/Risultati!G9*360),"0") -> 13.507173 | BV10: =IF(OR(E10="abbreviato",Risultati!G9=0),"0",((Risultati!AC9+Risultati!AD9)/Risultati!G9*360)) -> 6.8942232 | BW10: =IF(OR(E10="abbreviato",Risultati!G9=0,SUM(Risultati!I9+Risultati!K9+Risultati!M9)=0),"0",(((Risultati!AH9+Risultati!AI9)/(Risultati!I9+Risultati!K9+Risultati!N9)*360))) -> 53.649267 | BX10: =IF(Risultati!AB9>0,(+Risultati!AG9/Risultati!AB9),"0") -> 0.60689592 | BY10: =IF(OR(E10="abbreviato",Risultati!G9=0),"0",(((Risultati!AK9-(Risultati!AL9+Risultati!AM9))/Risultati!G9))) -> -0.0090867899 | BZ10: =IF(Risultati!G9>0,(Risultati!AJ9/Risultati!G9),"0") -> 0.16535188 | CB10: =+Risultati!AP9 -> 0 | CC10: =IF($CX10>0,(CB10/$CX10),"0") -> 0 | CD10: =+Risultati!AQ9 -> 18418 | CE10: =IF($CX10>0,(CD10/$CX10),"0") -> 0.013551964 | CF10: =+Risultati!AR9 -> 1074920 | CG10: =IF($CX10>0,(CF10/$CX10),"0") -> 0.79092611 | CH10: =+Risultati!AS9 -> 858 | CI10: =IF($CX10>0,(CH10/$CX10),"0") -> 0.00063131638 | CJ10: =+CH10+CF10+CD10 -> 1094196 | CK10: =IF($CX10>0,(CJ10/$CX10),"0") -> 0.8051094 | CL10: =+Risultati!AE9+Risultati!AF9 -> 118661 | CM10: =IF($CX10>0,(CL10/$CX10),"0") -> 0.087310761 | CN10: =+Risultati!AT9 -> 105277 | CO10: =IF($CX10>0,(CN10/$CX10),"0") -> 0.077462815 | CP10: =+Risultati!AU9 -> 1561 | CQ10: =IF($CX10>0,(CP10/$CX10),"0") -> 0.0011485838 | CR10: =+Risultati!AL9 -> 37692 | CS10: =IF($CX10>0,(CR10/$CX10),"0") -> 0.027733773 | CT10: =+CR10+CP10+CN10+CL10 -> 263191 | CU10: =IF($CX10>0,(CT10/$CX10),"0") -> 0.19365593 | CV10: =+Risultati!AX9 -> 1678 | CW10: =IF($CX10>0,(CV10/$CX10),"0") -> 0.0012346724 | CX10: =+CV10+CT10+CJ10 -> 1359065 | CY10: =IF($CX10>0,(CX10/$CX10),"0") -> 1 | CZ10: =+Risultati!AG9 -> 824811 | DA10: =IF($CX10>0,(CZ10/$CX10),"0") -> 0.60689592 | DB10: =+DL10-CZ10-DD10-DJ10 -> 3146 | DC10: =IF($CX10>0,(DB10/$CX10),"0") -> 0.0023148267 | DD10: =+Risultati!AV9 -> 522997 | DE10: =IF($CX10>0,(DD10/$CX10),"0") -> 0.38482118 | DF10: =+Risultati!AJ9 -> 522944 | DG10: =IF($CX10>0,(DF10/$CX10),"0") -> 0.38478218 | DH10: =+DD10-DF10 -> 53 | DI10: =IF($CX10>0,(DH10/$CX10),"0") -> 3.8997399e-05 | DJ10: =+Risultati!AW9 -> 8111 | DK10: =IF($CX10>0,(DJ10/$CX10),"0") -> 0.0059680736 | DL10: =+CX10 -> 1359065 | DM10: =IF($CX10>0,(DL10/$CX10),"0") -> 1
B11: =+Risultati!B10 -> UNICOOP FIRENZE SOCIETA' COOPERATIVA IN SIGLA UNICOOP FIRENZE SC | C11: =+Risultati!C10 -> 00407780485 | D11: =IF(YEAR(Risultati!D10)=1900,(MID(Risultati!$AP$1,29,4)),YEAR(Risultati!D10)) -> 2023 | E11: =+Risultati!E10 -> Dettagliato | F11: =(LEFT(Risultati!AN10,2)&"-")&VLOOKUP((LEFT(Risultati!AN10,2)),ateco!$B$4:$C$93,2,FALSE) -> 47-Commercio al dettaglio (escluso quello di autoveicoli e di motocicli) | G11: =SUBSTITUTE((Risultati!AN10&"-"&Risultati!AO10),",",";") -> 471120-Supermercati | I11: =+Risultati!G10 -> 3014665 | J11: =IF(L11<>0,(I11/L11),"0") -> 1 | L11: =+Risultati!G10+Risultati!H10 -> 3014665 | M11: =IF(L11<>0,(L11/(L11+U11)),"0") -> 0.96290319 | O11: =+Risultati!I10+Risultati!J10 -> 2408177 | P11: =IF(L11<>0,(O11/(L11+U11)),"0") -> 0.76918706 | R11: =+L11-O11 -> 606488 | S11: =IF(L11<>0,(R11/(L11+U11)),"0") -> 0.19371613 | U11: =+Risultati!F10-(Risultati!G10+Risultati!H10) -> 116143 | V11: =IF(L11<>0,(U11/(L11+U11)),"0") -> 0.037096813 | X11: =+U11+R11 -> 722631 | Y11: =IF(L11<>0,(X11/(L11+U11)),"0") -> 0.23081294 | AA11: =+Risultati!K10 -> 246066 | AB11: =IF(L11<>0,(AA11/(L11+U11)),"0") -> 0.078595046 | AD11: =+Risultati!L10 -> 290560 | AE11: =IF(L11<>0,(AD11/(L11+U11)),"0") -> 0.092806713 | AG11: =+Risultati!M10+Risultati!P10+Risultati!Q10 -> 76973 | AH11: =IF(L11<>0,(AG11/(L11+U11)),"0") -> 0.024585666 | AJ11: =+X11-AA11-AD11-AG11 -> 109032 | AK11: =IF(L11<>0,(AJ11/(L11+U11)),"0") -> 0.034825515 | AM11: =+Risultati!N10 -> 8481 | AN11: =IF(L11<>0,(AM11/(L11+U11)),"0") -> 0.0027088854 | AP11: =+AJ11-AM11 -> 100551 | AQ11: =IF(L11<>0,(AP11/(L11+U11)),"0") -> 0.032116629 | AS11: =+Risultati!O10 -> 99612 | AT11: =IF(L11<>0,(AS11/(L11+U11)),"0") -> 0.031816707 | AV11: =+AP11-AS11 -> 939 | AW11: =IF(L11<>0,(AV11/(L11+U11)),"0") -> 0.00029992258 | AY11: =+Risultati!R10+Risultati!S10 -> 36002 | AZ11: =IF(L11<>0,(AY11/(L11+U11)),"0") -> 0.011499268 | BB11: =+Risultati!T10 -> 0 | BC11: =IF(L11<>0,(BB11/(L11+U11)),"0") -> 0 | BE11: =+Risultati!U10 -> 11377 | BF11: =IF(L11<>0,(BE11/(L11+U11)),"0") -> 0.0036338862 | BH11: =+AV11+AY11+BB11-BE11 -> 25564 | BI11: =IF(L11<>0,(+BH11/(L11+U11)),"0") -> 0.0081653043 | BK11: =IF(ISNUMBER(Risultati!X10/100),(Risultati!X10/100)) -> 0.111997 | BL11: =IF(ISNUMBER(Risultati!Y10/100),(Risultati!Y10/100)) -> 0.24896167 | BM11: =IF(ISNUMBER(Risultati!Z10/100),(Risultati!Z10/100)) -> 0.26468763 | BN11: =IF(AND(Risultati!AY10<0,calcoli!AP11<0),-IF(ISNUMBER(Risultati!AA10/100),(Risultati!AA10/100)),IF(ISNUMBER(Risultati!AA10/100),(Risultati!AA10/100))) -> -0.36931897 | BO11: =+BI11 -> 0.0081653043 | BP11: =IF(Risultati!AB10>0,(AV11/Risultati!AB10),"0") -> 0.0002466708 | BQ11: =IF(Risultati!AG10<>0,(BH11/Risultati!AG10),"0") -> 0.014354862 | BR11: =+BI11 -> 0.0081653043 | BS11: =IF(Risultati!AB10>0,(Risultati!G10/Risultati!AB10),"0") -> 0.79193804 | BT11: =IF(Risultati!AG10<>0,(Risultati!AB10/Risultati!AG10),"0") -> 2.1375588 | BU11: =IF(AND(Risultati!G10>0,(Risultati!AE10-Risultati!AF10)>=0),((Risultati!AE10-Risultati!AF10)/Risultati!G10*360),"0") -> 14.673989 | BV11: =IF(OR(E11="abbreviato",Risultati!G10=0),"0",((Risultati!AC10+Risultati!AD10)/Risultati!G10*360)) -> 10.695278 | BW11: =IF(OR(E11="abbreviato",Risultati!G10=0,SUM(Risultati!I10+Risultati!K10+Risultati!M10)=0),"0",(((Risultati!AH10+Risultati!AI10)/(Risultati!I10+Risultati!K10+Risultati!N10)*360))) -> 58.347757 | BX11: =IF(Risultati!AB10>0,(+Risultati!AG10/Risultati!AB10),"0") -> 0.46782338 | BY11: =IF(OR(E11="abbreviato",Risultati!G10=0),"0",(((Risultati!AK10-(Risultati!AL10+Risultati!AM10))/Risultati!G10))) -> 0.39332463 | BZ11: =IF(Risultati!G10>0,(Risultati!AJ10/Risultati!G10),"0") -> 0.59206678 | CB11: =+Risultati!AP10 -> 0 | CC11: =IF($CX11>0,(CB11/$CX11),"0") -> 0 | CD11: =+Risultati!AQ10 -> 36851 | CE11: =IF($CX11>0,(CD11/$CX11),"0") -> 0.0096805836 | CF11: =+Risultati!AR10 -> 1375389 | CG11: =IF($CX11>0,(CF11/$CX11),"0") -> 0.36130819 | CH11: =+Risultati!AS10 -> 1252493 | CI11: =IF($CX11>0,(CH11/$CX11),"0") -> 0.32902399 | CJ11: =+CH11+CF11+CD11 -> 2664733 | CK11: =IF($CX11>0,(CJ11/$CX11),"0") -> 0.70001277 | CL11: =+Risultati!AE10+Risultati!AF10 -> 164563 | CM11: =IF($CX11>0,(CL11/$CX11),"0") -> 0.043229922 | CN11: =+Risultati!AT10 -> 241745 | CO11: =IF($CX11>0,(CN11/$CX11),"0") -> 0.063505269 | CP11: =+Risultati!AU10 -> 513026 | CQ11: =IF($CX11>0,(CP11/$CX11),"0") -> 0.13476951 | CR11: =+Risultati!AL10 -> 210389 | CS11: =IF($CX11>0,(CR11/$CX11),"0") -> 0.055268196 | CT11: =+CR11+CP11+CN11+CL11 -> 1129723 | CU11: =IF($CX11>0,(CT11/$CX11),"0") -> 0.29677289 | CV11: =+Risultati!AX10 -> 12236 | CW11: =IF($CX11>0,(CV11/$CX11),"0") -> 0.0032143394 | CX11: =+CV11+CT11+CJ11 -> 3806692 | CY11: =IF($CX11>0,(CX11/$CX11),"0") -> 1 | CZ11: =+Risultati!AG10 -> 1780860 | DA11: =IF($CX11>0,(CZ11/$CX11),"0") -> 0.46782351 | DB11: =+DL11-CZ11-DD11-DJ11 -> 90795 | DC11: =IF($CX11>0,(DB11/$CX11),"0") -> 0.023851417 | DD11: =+Risultati!AV10 -> 1934073 | DE11: =IF($CX11>0,(DD11/$CX11),"0") -> 0.50807184 | DF11: =+Risultati!AJ10 -> 1784883 | DG11: =IF($CX11>0,(DF11/$CX11),"0") -> 0.46888033 | DH11: =+DD11-DF11 -> 149190 | DI11: =IF($CX11>0,(DH11/$CX11),"0") -> 0.039191508 | DJ11: =+Risultati!AW10 -> 964 | DK11: =IF($CX11>0,(DJ11/$CX11),"0") -> 0.00025323824 | DL11: =+CX11 -> 3806692 | DM11: =IF($CX11>0,(DL11/$CX11),"0") -> 1
B12: =+Risultati!B11 -> CONAD NORD OVEST SOCIETA' COOPERATIVA | C12: =+Risultati!C11 -> 01977130473 | D12: =IF(YEAR(Risultati!D11)=1900,(MID(Risultati!$AP$1,29,4)),YEAR(Risultati!D11)) -> 2023 | E12: =+Risultati!E11 -> Dettagliato | F12: =(LEFT(Risultati!AN11,2)&"-")&VLOOKUP((LEFT(Risultati!AN11,2)),ateco!$B$4:$C$93,2,FALSE) -> 46-Commercio all'ingrosso (escluso quello di autoveicoli e di motocicli) | G12: =SUBSTITUTE((Risultati!AN11&"-"&Risultati!AO11),",",";") -> 463920-Commercio all'ingrosso non specializzato di prodotti alimentari; bevande e tabacco | I12: =+Risultati!G11 -> 2997446 | J12: =IF(L12<>0,(I12/L12),"0") -> 1 | L12: =+Risultati!G11+Risultati!H11 -> 2997446 | M12: =IF(L12<>0,(L12/(L12+U12)),"0") -> 0.89174112 | O12: =+Risultati!I11+Risultati!J11 -> 3049124 | P12: =IF(L12<>0,(O12/(L12+U12)),"0") -> 0.90711534 | R12: =+L12-O12 -> -51678 | S12: =IF(L12<>0,(R12/(L12+U12)),"0") -> -0.015374221 | U12: =+Risultati!F11-(Risultati!G11+Risultati!H11) -> 363895 | V12: =IF(L12<>0,(U12/(L12+U12)),"0") -> 0.10825888 | X12: =+U12+R12 -> 312217 | Y12: =IF(L12<>0,(X12/(L12+U12)),"0") -> 0.092884655 | AA12: =+Risultati!K11 -> 202421 | AB12: =IF(L12<>0,(AA12/(L12+U12)),"0") -> 0.060220311 | AD12: =+Risultati!L11 -> 31138 | AE12: =IF(L12<>0,(AD12/(L12+U12)),"0") -> 0.0092635647 | AG12: =+Risultati!M11+Risultati!P11+Risultati!Q11 -> 6359 | AH12: =IF(L12<>0,(AG12/(L12+U12)),"0") -> 0.0018918045 | AJ12: =+X12-AA12-AD12-AG12 -> 72299 | AK12: =IF(L12<>0,(AJ12/(L12+U12)),"0") -> 0.021508975 | AM12: =+Risultati!N11 -> 0 | AN12: =IF(L12<>0,(AM12/(L12+U12)),"0") -> 0 | AP12: =+AJ12-AM12 -> 72299 | AQ12: =IF(L12<>0,(AP12/(L12+U12)),"0") -> 0.021508975 | AS12: =+Risultati!O11 -> 25543 | AT12: =IF(L12<>0,(AS12/(L12+U12)),"0") -> 0.0075990505 | AV12: =+AP12-AS12 -> 46756 | AW12: =IF(L12<>0,(AV12/(L12+U12)),"0") -> 0.013909925 | AY12: =+Risultati!R11+Risultati!S11 -> 15910 | AZ12: =IF(L12<>0,(AY12/(L12+U12)),"0") -> 0.00473323 | BB12: =+Risultati!T11 -> -448 | BC12: =IF(L12<>0,(BB12/(L12+U12)),"0") -> -0.00013328014 | BE12: =+Risultati!U11 -> 1315 | BF12: =IF(L12<>0,(BE12/(L12+U12)),"0") -> 0.00039121291 | BH12: =+AV12+AY12+BB12-BE12 -> 60903 | BI12: =IF(L12<>0,(+BH12/(L12+U12)),"0") -> 0.018118662 | BK12: =IF(ISNUMBER(Risultati!X11/100),(Risultati!X11/100)) -> 0.077557885 | BL12: =IF(ISNUMBER(Risultati!Y11/100),(Risultati!Y11/100)) -> 0.15880226 | BM12: =IF(ISNUMBER(Risultati!Z11/100),(Risultati!Z11/100)) -> 0.24223553 | BN12: =IF(AND(Risultati!AY11<0,calcoli!AP12<0),-IF(ISNUMBER(Risultati!AA11/100),(Risultati!AA11/100)),IF(ISNUMBER(Risultati!AA11/100),(Risultati!AA11/100))) -> 0.36192216 | BO12: =+BI12 -> 0.018118662 | BP12: =IF(Risultati!AB11>0,(AV12/Risultati!AB11),"0") -> 0.024188846 | BQ12: =IF(Risultati!AG11<>0,(BH12/Risultati!AG11),"0") -> 0.066021731 | BR12: =+BI12 -> 0.018118662 | BS12: =IF(Risultati!AB11>0,(Risultati!G11/Risultati!AB11),"0") -> 1.550705 | BT12: =IF(Risultati!AG11<>0,(Risultati!AB11/Risultati!AG11),"0") -> 2.0954168 | BU12: =IF(AND(Risultati!G11>0,(Risultati!AE11-Risultati!AF11)>=0),((Risultati!AE11-Risultati!AF11)/Risultati!G11*360),"0") -> 15.553721 | BV12: =IF(OR(E12="abbreviato",Risultati!G11=0),"0",((Risultati!AC11+Risultati!AD11)/Risultati!G11*360)) -> 13.662231 | BW12: =IF(OR(E12="abbreviato",Risultati!G11=0,SUM(Risultati!I11+Risultati!K11+Risultati!M11)=0),"0",(((Risultati!AH11+Risultati!AI11)/(Risultati!I11+Risultati!K11+Risultati!N11)*360))) -> 40.971937 | BX12: =IF(Risultati!AB11>0,(+Risultati!AG11/Risultati!AB11),"0") -> 0.47723203 | BY12: =IF(OR(E12="abbreviato",Risultati!G11=0),"0",(((Risultati!AK11-(Risultati!AL11+Risultati!AM11))/Risultati!G11))) -> 0.11637641 | BZ12: =IF(Risultati!G11>0,(Risultati!AJ11/Risultati!G11),"0") -> 0.20572414 | CB12: =+Risultati!AP11 -> 0 | CC12: =IF($CX12>0,(CB12/$CX12),"0") -> 0 | CD12: =+Risultati!AQ11 -> 75454 | CE12: =IF($CX12>0,(CD12/$CX12),"0") -> 0.03903553 | CF12: =+Risultati!AR11 -> 117115 | CG12: =IF($CX12>0,(CF12/$CX12),"0") -> 0.060588518 | CH12: =+Risultati!AS11 -> 596019 | CI12: =IF($CX12>0,(CH12/$CX12),"0") -> 0.30834571 | CJ12: =+CH12+CF12+CD12 -> 788588 | CK12: =IF($CX12>0,(CJ12/$CX12),"0") -> 0.40796976 | CL12: =+Risultati!AE11+Risultati!AF11 -> 129504 | CM12: =IF($CX12>0,(CL12/$CX12),"0") -> 0.066997869 | CN12: =+Risultati!AT11 -> 644162 | CO12: =IF($CX12>0,(CN12/$CX12),"0") -> 0.33325211 | CP12: =+Risultati!AU11 -> 213958 | CQ12: =IF($CX12>0,(CP12/$CX12),"0") -> 0.11068948 | CR12: =+Risultati!AL11 -> 156745 | CS12: =IF($CX12>0,(CR12/$CX12),"0") -> 0.081090785 | CT12: =+CR12+CP12+CN12+CL12 -> 1144369 | CU12: =IF($CX12>0,(CT12/$CX12),"0") -> 0.59203024 | CV12: =+Risultati!AX11 -> 0 | CW12: =IF($CX12>0,(CV12/$CX12),"0") -> 0 | CX12: =+CV12+CT12+CJ12 -> 1932957 | CY12: =IF($CX12>0,(CX12/$CX12),"0") -> 1 | CZ12: =+Risultati!AG11 -> 922469 | DA12: =IF($CX12>0,(CZ12/$CX12),"0") -> 0.47723203 | DB12: =+DL12-CZ12-DD12-DJ12 -> 28231 | DC12: =IF($CX12>0,(DB12/$CX12),"0") -> 0.014605084 | DD12: =+Risultati!AV11 -> 977455 | DE12: =IF($CX12>0,(DD12/$CX12),"0") -> 0.50567861 | DF12: =+Risultati!AJ11 -> 616647 | DG12: =IF($CX12>0,(DF12/$CX12),"0") -> 0.31901744 | DH12: =+DD12-DF12 -> 360808 | DI12: =IF($CX12>0,(DH12/$CX12),"0") -> 0.18666116 | DJ12: =+Risultati!AW11 -> 4802 | DK12: =IF($CX12>0,(DJ12/$CX12),"0") -> 0.0024842767 | DL12: =+CX12 -> 1932957 | DM12: =IF($CX12>0,(DL12/$CX12),"0") -> 1
B13: =+Risultati!B12 -> AGRICOLA TRE VALLI - SOCIETA' COOPERATIVA | C13: =+Risultati!C12 -> 02447620234 | D13: =IF(YEAR(Risultati!D12)=1900,(MID(Risultati!$AP$1,29,4)),YEAR(Risultati!D12)) -> 2023 | E13: =+Risultati!E12 -> Dettagliato | F13: =(LEFT(Risultati!AN12,2)&"-")&VLOOKUP((LEFT(Risultati!AN12,2)),ateco!$B$4:$C$93,2,FALSE) -> 10-Industrie alimentari | G13: =SUBSTITUTE((Risultati!AN12&"-"&Risultati!AO12),",",";") -> 101200-Produzione di carne di volatili e prodotti della loro macellazione (attività dei mattatoi) | I13: =+Risultati!G12 -> 2912605 | J13: =IF(L13<>0,(I13/L13),"0") -> 0.99643997 | L13: =+Risultati!G12+Risultati!H12 -> 2923011 | M13: =IF(L13<>0,(L13/(L13+U13)),"0") -> 0.99461725 | O13: =+Risultati!I12+Risultati!J12 -> 2189179 | P13: =IF(L13<>0,(O13/(L13+U13)),"0") -> 0.74491515 | R13: =+L13-O13 -> 733832 | S13: =IF(L13<>0,(R13/(L13+U13)),"0") -> 0.24970209 | U13: =+Risultati!F12-(Risultati!G12+Risultati!H12) -> 15819 | V13: =IF(L13<>0,(U13/(L13+U13)),"0") -> 0.0053827544 | X13: =+U13+R13 -> 749651 | Y13: =IF(L13<>0,(X13/(L13+U13)),"0") -> 0.25508485 | AA13: =+Risultati!K12 -> 334610 | AB13: =IF(L13<>0,(AA13/(L13+U13)),"0") -> 0.11385824 | AD13: =+Risultati!L12 -> 300149 | AE13: =IF(L13<>0,(AD13/(L13+U13)),"0") -> 0.10213214 | AG13: =+Risultati!M12+Risultati!P12+Risultati!Q12 -> 10453 | AH13: =IF(L13<>0,(AG13/(L13+U13)),"0") -> 0.0035568577 | AJ13: =+X13-AA13-AD13-AG13 -> 104439 | AK13: =IF(L13<>0,(AJ13/(L13+U13)),"0") -> 0.035537612 | AM13: =+Risultati!N12 -> 101593 | AN13: =IF(L13<>0,(AM13/(L13+U13)),"0") -> 0.034569199 | AP13: =+AJ13-AM13 -> 2846 | AQ13: =IF(L13<>0,(AP13/(L13+U13)),"0") -> 0.0009684126 | AS13: =+Risultati!O12 -> 1875 | AT13: =IF(L13<>0,(AS13/(L13+U13)),"0") -> 0.000638009 | AV13: =+AP13-AS13 -> 971 | AW13: =IF(L13<>0,(AV13/(L13+U13)),"0") -> 0.0003304036 | AY13: =+Risultati!R12+Risultati!S12 -> -758 | AZ13: =IF(L13<>0,(AY13/(L13+U13)),"0") -> -0.00025792577 | BB13: =+Risultati!T12 -> 0 | BC13: =IF(L13<>0,(BB13/(L13+U13)),"0") -> 0 | BE13: =+Risultati!U12 -> 23 | BF13: =IF(L13<>0,(BE13/(L13+U13)),"0") -> 7.8262438e-06 | BH13: =+AV13+AY13+BB13-BE13 -> 190 | BI13: =IF(L13<>0,(+BH13/(L13+U13)),"0") -> 6.4651579e-05 | BK13: =IF(ISNUMBER(Risultati!X12/100),(Risultati!X12/100)) -> 0.13829881 | BL13: =IF(ISNUMBER(Risultati!Y12/100),(Risultati!Y12/100)) -> 0.21306228 | BM13: =IF(ISNUMBER(Risultati!Z12/100),(Risultati!Z12/100)) -> 0.31697986 | BN13: =IF(AND(Risultati!AY12<0,calcoli!AP13<0),-IF(ISNUMBER(Risultati!AA12/100),(Risultati!AA12/100)),IF(ISNUMBER(Risultati!AA12/100),(Risultati!AA12/100))) -> -0.31006061 | BO13: =+BI13 -> 6.4651579e-05 | BP13: =IF(Risultati!AB12>0,(AV13/Risultati!AB12),"0") -> 0.0021132263 | BQ13: =IF(Risultati!AG12<>0,(BH13/Risultati!AG12),"0") -> 0.008033487 | BR13: =+BI13 -> 6.4651579e-05 | BS13: =IF(Risultati!AB12>0,(Risultati!G12/Risultati!AB12),"0") -> 6.3388192 | BT13: =IF(Risultati!AG12<>0,(Risultati!AB12/Risultati!AG12),"0") -> 19.427804 | BU13: =IF(AND(Risultati!G12>0,(Risultati!AE12-Risultati!AF12)>=0),((Risultati!AE12-Risultati!AF12)/Risultati!G12*360),"0") -> 29.415606 | BV13: =IF(OR(E13="abbreviato",Risultati!G12=0),"0",((Risultati!AC12+Risultati!AD12)/Risultati!G12*360)) -> 20.195241 | BW13: =IF(OR(E13="abbreviato",Risultati!G12=0,SUM(Risultati!I12+Risultati!K12+Risultati!M12)=0),"0",(((Risultati!AH12+Risultati!AI12)/(Risultati!I12+Risultati!K12+Risultati!N12)*360))) -> 39.172337 | BX13: =IF(Risultati!AB12>0,(+Risultati!AG12/Risultati!AB12),"0") -> 0.051472621 | BY13: =IF(OR(E13="abbreviato",Risultati!G12=0),"0",(((Risultati!AK12-(Risultati!AL12+Risultati!AM12))/Risultati!G12))) -> 0.015079971 | BZ13: =IF(Risultati!G12>0,(Risultati!AJ12/Risultati!G12),"0") -> 0.14112659 | CB13: =+Risultati!AP12 -> 0 | CC13: =IF($CX13>0,(CB13/$CX13),"0") -> 0 | CD13: =+Risultati!AQ12 -> 84 | CE13: =IF($CX13>0,(CD13/$CX13),"0") -> 0.00018281297 | CF13: =+Risultati!AR12 -> 11237 | CG13: =IF($CX13>0,(CF13/$CX13),"0") -> 0.024455587 | CH13: =+Risultati!AS12 -> 69 | CI13: =IF($CX13>0,(CH13/$CX13),"0") -> 0.0001501678 | CJ13: =+CH13+CF13+CD13 -> 11390 | CK13: =IF($CX13>0,(CJ13/$CX13),"0") -> 0.024788568 | CL13: =+Risultati!AE12+Risultati!AF12 -> 237989 | CM13: =IF($CX13>0,(CL13/$CX13),"0") -> 0.51794614 | CN13: =+Risultati!AT12 -> 209214 | CO13: =IF($CX13>0,(CN13/$CX13),"0") -> 0.45532182 | CP13: =+Risultati!AU12 -> 0 | CQ13: =IF($CX13>0,(CP13/$CX13),"0") -> 0 | CR13: =+Risultati!AL12 -> 622 | CS13: =IF($CX13>0,(CR13/$CX13),"0") -> 0.0013536865 | CT13: =+CR13+CP13+CN13+CL13 -> 447825 | CU13: =IF($CX13>0,(CT13/$CX13),"0") -> 0.97462164 | CV13: =+Risultati!AX12 -> 271 | CW13: =IF($CX13>0,(CV13/$CX13),"0") -> 0.00058978946 | CX13: =+CV13+CT13+CJ13 -> 459486 | CY13: =IF($CX13>0,(CX13/$CX13),"0") -> 1 | CZ13: =+Risultati!AG12 -> 23651 | DA13: =IF($CX13>0,(CZ13/$CX13),"0") -> 0.051472733 | DB13: =+DL13-CZ13-DD13-DJ13 -> 24545 | DC13: =IF($CX13>0,(DB13/$CX13),"0") -> 0.053418385 | DD13: =+Risultati!AV12 -> 411046 | DE13: =IF($CX13>0,(DD13/$CX13),"0") -> 0.89457785 | DF13: =+Risultati!AJ12 -> 411046 | DG13: =IF($CX13>0,(DF13/$CX13),"0") -> 0.89457785 | DH13: =+DD13-DF13 -> 0 | DI13: =IF($CX13>0,(DH13/$CX13),"0") -> 0 | DJ13: =+Risultati!AW12 -> 244 | DK13: =IF($CX13>0,(DJ13/$CX13),"0") -> 0.00053102815 | DL13: =+CX13 -> 459486 | DM13: =IF($CX13>0,(DL13/$CX13),"0") -> 1
B14: =+Risultati!B13 -> MAXI DI S.R.L. | C14: =+Risultati!C13 -> 00542090238 | D14: =IF(YEAR(Risultati!D13)=1900,(MID(Risultati!$AP$1,29,4)),YEAR(Risultati!D13)) -> 2023 | E14: =+Risultati!E13 -> Dettagliato | F14: =(LEFT(Risultati!AN13,2)&"-")&VLOOKUP((LEFT(Risultati!AN13,2)),ateco!$B$4:$C$93,2,FALSE) -> 47-Commercio al dettaglio (escluso quello di autoveicoli e di motocicli) | G14: =SUBSTITUTE((Risultati!AN13&"-"&Risultati!AO13),",",";") -> 471120-Supermercati | I14: =+Risultati!G13 -> 2690365 | J14: =IF(L14<>0,(I14/L14),"0") -> 1 | L14: =+Risultati!G13+Risultati!H13 -> 2690365 | M14: =IF(L14<>0,(L14/(L14+U14)),"0") -> 0.98491058 | O14: =+Risultati!I13+Risultati!J13 -> 2013236 | P14: =IF(L14<>0,(O14/(L14+U14)),"0") -> 0.73702172 | R14: =+L14-O14 -> 677129 | S14: =IF(L14<>0,(R14/(L14+U14)),"0") -> 0.24788886 | U14: =+Risultati!F13-(Risultati!G13+Risultati!H13) -> 41218 | V14: =IF(L14<>0,(U14/(L14+U14)),"0") -> 0.015089419 | X14: =+U14+R14 -> 718347 | Y14: =IF(L14<>0,(X14/(L14+U14)),"0") -> 0.26297828 | AA14: =+Risultati!K13 -> 251200 | AB14: =IF(L14<>0,(AA14/(L14+U14)),"0") -> 0.091961328 | AD14: =+Risultati!L13 -> 226369 | AE14: =IF(L14<>0,(AD14/(L14+U14)),"0") -> 0.082870995 | AG14: =+Risultati!M13+Risultati!P13+Risultati!Q13 -> 18601 | AH14: =IF(L14<>0,(AG14/(L14+U14)),"0") -> 0.0068096045 | AJ14: =+X14-AA14-AD14-AG14 -> 222177 | AK14: =IF(L14<>0,(AJ14/(L14+U14)),"0") -> 0.081336353 | AM14: =+Risultati!N13 -> 40000 | AN14: =IF(L14<>0,(AM14/(L14+U14)),"0") -> 0.014643524 | AP14: =+AJ14-AM14 -> 182177 | AQ14: =IF(L14<>0,(AP14/(L14+U14)),"0") -> 0.06669283 | AS14: =+Risultati!O13 -> 83683 | AT14: =IF(L14<>0,(AS14/(L14+U14)),"0") -> 0.03063535 | AV14: =+AP14-AS14 -> 98494 | AW14: =IF(L14<>0,(AV14/(L14+U14)),"0") -> 0.03605748 | AY14: =+Risultati!R13+Risultati!S13 -> 1450 | AZ14: =IF(L14<>0,(AY14/(L14+U14)),"0") -> 0.00053082773 | BB14: =+Risultati!T13 -> 0 | BC14: =IF(L14<>0,(BB14/(L14+U14)),"0") -> 0 | BE14: =+Risultati!U13 -> 25213 | BF14: =IF(L14<>0,(BE14/(L14+U14)),"0") -> 0.009230179 | BH14: =+AV14+AY14+BB14-BE14 -> 74731 | BI14: =IF(L14<>0,(+BH14/(L14+U14)),"0") -> 0.027358129 | BK14: =IF(ISNUMBER(Risultati!X13/100),(Risultati!X13/100)) -> 0.089094903 | BL14: =IF(ISNUMBER(Risultati!Y13/100),(Risultati!Y13/100)) -> 0.12712543 | BM14: =IF(ISNUMBER(Risultati!Z13/100),(Risultati!Z13/100)) -> 0.26621083 | BN14: =IF(AND(Risultati!AY13<0,calcoli!AP14<0),-IF(ISNUMBER(Risultati!AA13/100),(Risultati!AA13/100)),IF(ISNUMBER(Risultati!AA13/100),(Risultati!AA13/100))) -> 0.45118172 | BO14: =+BI14 -> 0.027358129 | BP14: =IF(Risultati!AB13>0,(AV14/Risultati!AB13),"0") -> 0.072571471 | BQ14: =IF(Risultati!AG13<>0,(BH14/Risultati!AG13),"0") -> 0.10392845 | BR14: =+BI14 -> 0.027358129 | BS14: =IF(Risultati!AB13>0,(Risultati!G13/Risultati!AB13),"0") -> 1.9822907 | BT14: =IF(Risultati!AG13<>0,(Risultati!AB13/Risultati!AG13),"0") -> 1.8874589 | BU14: =IF(AND(Risultati!G13>0,(Risultati!AE13-Risultati!AF13)>=0),((Risultati!AE13-Risultati!AF13)/Risultati!G13*360),"0") -> 39.102739 | BV14: =IF(OR(E14="abbreviato",Risultati!G13=0),"0",((Risultati!AC13+Risultati!AD13)/Risultati!G13*360)) -> 3.9391235 | BW14: =IF(OR(E14="abbreviato",Risultati!G13=0,SUM(Risultati!I13+Risultati!K13+Risultati!M13)=0),"0",(((Risultati!AH13+Risultati!AI13)/(Risultati!I13+Risultati!K13+Risultati!N13)*360))) -> 49.596994 | BX14: =IF(Risultati!AB13>0,(+Risultati!AG13/Risultati!AB13),"0") -> 0.52981285 | BY14: =IF(OR(E14="abbreviato",Risultati!G13=0),"0",(((Risultati!AK13-(Risultati!AL13+Risultati!AM13))/Risultati!G13))) -> 0.039943651 | BZ14: =IF(Risultati!G13>0,(Risultati!AJ13/Risultati!G13),"0") -> 0.16538871 | CB14: =+Risultati!AP13 -> 0 | CC14: =IF($CX14>0,(CB14/$CX14),"0") -> 0 | CD14: =+Risultati!AQ13 -> 36444 | CE14: =IF($CX14>0,(CD14/$CX14),"0") -> 0.026852323 | CF14: =+Risultati!AR13 -> 771154 | CG14: =IF($CX14>0,(CF14/$CX14),"0") -> 0.56819439 | CH14: =+Risultati!AS13 -> 68729 | CI14: =IF($CX14>0,(CH14/$CX14),"0") -> 0.050640252 | CJ14: =+CH14+CF14+CD14 -> 876327 | CK14: =IF($CX14>0,(CJ14/$CX14),"0") -> 0.64568697 | CL14: =+Risultati!AE13+Risultati!AF13 -> 292224 | CM14: =IF($CX14>0,(CL14/$CX14),"0") -> 0.21531372 | CN14: =+Risultati!AT13 -> 58277 | CO14: =IF($CX14>0,(CN14/$CX14),"0") -> 0.042939108 | CP14: =+Risultati!AU13 -> 0 | CQ14: =IF($CX14>0,(CP14/$CX14),"0") -> 0 | CR14: =+Risultati!AL13 -> 123845 | CS14: =IF($CX14>0,(CR14/$CX14),"0") -> 0.091250301 | CT14: =+CR14+CP14+CN14+CL14 -> 474346 | CU14: =IF($CX14>0,(CT14/$CX14),"0") -> 0.34950313 | CV14: =+Risultati!AX13 -> 6528 | CW14: =IF($CX14>0,(CV14/$CX14),"0") -> 0.0048098992 | CX14: =+CV14+CT14+CJ14 -> 1357201 | CY14: =IF($CX14>0,(CX14/$CX14),"0") -> 1 | CZ14: =+Risultati!AG13 -> 719062 | DA14: =IF($CX14>0,(CZ14/$CX14),"0") -> 0.52981246 | DB14: =+DL14-CZ14-DD14-DJ14 -> 14768 | DC14: =IF($CX14>0,(DB14/$CX14),"0") -> 0.010881218 | DD14: =+Risultati!AV13 -> 614979 | DE14: =IF($CX14>0,(DD14/$CX14),"0") -> 0.45312301 | DF14: =+Risultati!AJ13 -> 444956 | DG14: =IF($CX14>0,(DF14/$CX14),"0") -> 0.32784827 | DH14: =+DD14-DF14 -> 170023 | DI14: =IF($CX14>0,(DH14/$CX14),"0") -> 0.12527474 | DJ14: =+Risultati!AW13 -> 8392 | DK14: =IF($CX14>0,(DJ14/$CX14),"0") -> 0.006183314 | DL14: =+CX14 -> 1357201 | DM14: =IF($CX14>0,(DL14/$CX14),"0") -> 1
... B502: =+Risultati!B501 -> 0 | C502: =+Risultati!C501 -> 0 | D502: =IF(YEAR(Risultati!D501)=1900,(MID(Risultati!$AP$1,29,4)),YEAR(Risultati!D501)) | E502: =+Risultati!E501 -> 0 | F502: =(LEFT(Risultati!AN501,2)&"-")&VLOOKUP((LEFT(Risultati!AN501,2)),ateco!$B$4:$C$93,2,FALSE) -> #N/A | G502: =SUBSTITUTE((Risultati!AN501&"-"&Risultati!AO501),",",";") -> - | I502: =+Risultati!G501 -> 0 | J502: =IF(L502<>0,(I502/L502),"0") -> 0 | L502: =+Risultati!G501+Risultati!H501 -> 0 | M502: =IF(L502<>0,(L502/(L502+U502)),"0") -> 0 | O502: =+Risultati!I501+Risultati!J501 -> 0 | P502: =IF(L502<>0,(O502/(L502+U502)),"0") -> 0 | R502: =+L502-O502 -> 0 | S502: =IF(L502<>0,(R502/(L502+U502)),"0") -> 0 | U502: =+Risultati!F501-(Risultati!G501+Risultati!H501) -> 0 | V502: =IF(L502<>0,(U502/(L502+U502)),"0") -> 0 | X502: =+U502+R502 -> 0 | Y502: =IF(L502<>0,(X502/(L502+U502)),"0") -> 0 | AA502: =+Risultati!K501 -> 0 | AB502: =IF(L502<>0,(AA502/(L502+U502)),"0") -> 0 | AD502: =+Risultati!L501 -> 0 | AE502: =IF(L502<>0,(AD502/(L502+U502)),"0") -> 0 | AG502: =+Risultati!M501+Risultati!P501+Risultati!Q501 -> 0 | AH502: =IF(L502<>0,(AG502/(L502+U502)),"0") -> 0 | AJ502: =+X502-AA502-AD502-AG502 -> 0 | AK502: =IF(L502<>0,(AJ502/(L502+U502)),"0") -> 0 | AM502: =+Risultati!N501 -> 0 | AN502: =IF(L502<>0,(AM502/(L502+U502)),"0") -> 0 | AP502: =+AJ502-AM502 -> 0 | AQ502: =IF(L502<>0,(AP502/(L502+U502)),"0") -> 0 | AS502: =+Risultati!O501 -> 0 | AT502: =IF(L502<>0,(AS502/(L502+U502)),"0") -> 0 | AV502: =+AP502-AS502 -> 0 | AW502: =IF(L502<>0,(AV502/(L502+U502)),"0") -> 0 | AY502: =+Risultati!R501+Risultati!S501 -> 0 | AZ502: =IF(L502<>0,(AY502/(L502+U502)),"0") -> 0 | BB502: =+Risultati!T501 -> 0 | BC502: =IF(L502<>0,(BB502/(L502+U502)),"0") -> 0 | BE502: =+Risultati!U501 -> 0 | BF502: =IF(L502<>0,(BE502/(L502+U502)),"0") -> 0 | BH502: =+AV502+AY502+BB502-BE502 -> 0 | BI502: =IF(L502<>0,(+BH502/(L502+U502)),"0") -> 0 | BK502: =IF(ISNUMBER(Risultati!X501/100),(Risultati!X501/100)) -> 0 | BL502: =IF(ISNUMBER(Risultati!Y501/100),(Risultati!Y501/100)) -> 0 | BM502: =IF(ISNUMBER(Risultati!Z501/100),(Risultati!Z501/100)) -> 0 | BN502: =IF(AND(Risultati!AY501<0,calcoli!AP502<0),-IF(ISNUMBER(Risultati!AA501/100),(Risultati!AA501/100)),IF(ISNUMBER(Risultati!AA501/100),(Risultati!AA501/100))) -> 0 | BO502: =+BI502 -> 0 | BP502: =IF(Risultati!AB501>0,(AV502/Risultati!AB501),"0") -> 0 | BQ502: =IF(Risultati!AG501<>0,(BH502/Risultati!AG501),"0") -> 0 | BR502: =+BI502 -> 0 | BS502: =IF(Risultati!AB501>0,(Risultati!G501/Risultati!AB501),"0") -> 0 | BT502: =IF(Risultati!AG501<>0,(Risultati!AB501/Risultati!AG501),"0") -> 0 | BU502: =IF(AND(Risultati!G501>0,(Risultati!AE501-Risultati!AF501)>=0),((Risultati!AE501-Risultati!AF501)/Risultati!G501*360),"0") -> 0 | BV502: =IF(OR(E502="abbreviato",Risultati!G501=0),"0",((Risultati!AC501+Risultati!AD501)/Risultati!G501*360)) -> 0 | BW502: =IF(OR(E502="abbreviato",Risultati!G501=0,SUM(Risultati!I501+Risultati!K501+Risultati!M501)=0),"0",(((Risultati!AH501+Risultati!AI501)/(Risultati!I501+Risultati!K501+Risultati!N501)*360))) -> 0 | BX502: =IF(Risultati!AB501>0,(+Risultati!AG501/Risultati!AB501),"0") -> 0 | BY502: =IF(OR(E502="abbreviato",Risultati!G501=0),"0",(((Risultati!AK501-(Risultati!AL501+Risultati!AM501))/Risultati!G501))) -> 0 | BZ502: =IF(Risultati!G501>0,(Risultati!AJ501/Risultati!G501),"0") -> 0 | CB502: =+Risultati!AP501 -> 0 | CC502: =IF($CX502>0,(CB502/$CX502),"0") -> 0 | CD502: =+Risultati!AQ501 -> 0 | CE502: =IF($CX502>0,(CD502/$CX502),"0") -> 0 | CF502: =+Risultati!AR501 -> 0 | CG502: =IF($CX502>0,(CF502/$CX502),"0") -> 0 | CH502: =+Risultati!AS501 -> 0 | CI502: =IF($CX502>0,(CH502/$CX502),"0") -> 0 | CJ502: =+CH502+CF502+CD502 -> 0 | CK502: =IF($CX502>0,(CJ502/$CX502),"0") -> 0 | CL502: =+Risultati!AE501+Risultati!AF501 -> 0 | CM502: =IF($CX502>0,(CL502/$CX502),"0") -> 0 | CN502: =+Risultati!AT501 -> 0 | CO502: =IF($CX502>0,(CN502/$CX502),"0") -> 0 | CP502: =+Risultati!AU501 -> 0 | CQ502: =IF($CX502>0,(CP502/$CX502),"0") -> 0 | CR502: =+Risultati!AL501 -> 0 | CS502: =IF($CX502>0,(CR502/$CX502),"0") -> 0 | CT502: =+CR502+CP502+CN502+CL502 -> 0 | CU502: =IF($CX502>0,(CT502/$CX502),"0") -> 0 | CV502: =+Risultati!AX501 -> 0 | CW502: =IF($CX502>0,(CV502/$CX502),"0") -> 0 | CX502: =+CV502+CT502+CJ502 -> 0 | CY502: =IF($CX502>0,(CX502/$CX502),"0") -> 0 | CZ502: =+Risultati!AG501 -> 0 | DA502: =IF($CX502>0,(CZ502/$CX502),"0") -> 0 | DB502: =+DL502-CZ502-DD502-DJ502 -> 0 | DC502: =IF($CX502>0,(DB502/$CX502),"0") -> 0 | DD502: =+Risultati!AV501 -> 0 | DE502: =IF($CX502>0,(DD502/$CX502),"0") -> 0 | DF502: =+Risultati!AJ501 -> 0 | DG502: =IF($CX502>0,(DF502/$CX502),"0") -> 0 | DH502: =+DD502-DF502 -> 0 | DI502: =IF($CX502>0,(DH502/$CX502),"0") -> 0 | DJ502: =+Risultati!AW501 -> 0 | DK502: =IF($CX502>0,(DJ502/$CX502),"0") -> 0 | DL502: =+CX502 -> 0 | DM502: =IF($CX502>0,(DL502/$CX502),"0") -> 0

Sheet export
A1: Gruppo | B1: Ragione sociale | C1: P.Iva | D1: Anno | E1: Tipo di bilancio | F1: Classe | G1: Sottoclasse | H1: Nota Generale | I1: Fatturato | L1: Fatturato (100%) +/- Δ Rimanenze Prodotti | O1: Consumo di Materie Prime | R1: margine commerciale PURO | U1: Altri ricavi | X1: Margine Commerciale/INDUSTRIALE | AA1: Spese per Servizi | AD1: Costo del lavoro | AG1: +/- Altri Costi e Ricavi Operativi | AJ1: EBITDAR | AM1: Spese per affitti e noleggi | AP1: EBITDA margin | AS1: Ammortamenti e Svalutazioni | AV1: EBIT margin | AY1: Gestione finanziaria (interessi e rettifiche) | BB1: Gestione straordinaria | BE1: Imposte | BH1: Profit margin | BK1: Crescita Fatturato ultimo anno | BL1: Crescita Fatturato a 3 anni | BM1: Crescita Fatturato a 5 anni | BN1: crescita EBITDA 5 anni | BO1: Risultato d'Esercizio / Ricavi | BP1: ROI | BQ1: ROE | BR1: Profit Margin | BS1: Rotazione Attivo | BT1: Leva Finanziaria | BU1: Tempi medi giacenza Scorte (rimanenze/Fatturato)*360 | BV1: Tempi medi incasso (Clienti/Fatturato)*360 | BW1: Tempi medi pagamento (Fornitori/(Acquisti+Servizi+Affitti e noleggi))*360 | BX1: mezzi propri/attivo | BY1: debiti finanziari netti/ricavi | BZ1: Debiti a breve/ricavi | CA1: Aggregato | CB1: Crediti vs Soci | CC1: % | CD1: Immobilizzi immateriali | CE1: % | CF1: Immobilizzi materiali | CG1: % | CH1: Immobilizzi finanziari | CI1: % | CJ1: Totale Attivo Immobilizzato | CK1: % | CL1: Rimanenze | CM1: % | CN1: Crediti | CO1: % | CP1: Attività Finanziarie correnti | CQ1: % | CR1: Disponibilità Liquide | CS1: % | CT1: Totale Attivo Corrente | CU1: % | CV1: Ratei e Risconti Attivi | CW1: % | CX1: Totale Attivo | CY1: % | CZ1: Patrimonio Netto | DA1: % | DB1: Fondo TFR e Fondi Rischi | DC1: % | DD1: Debiti | DE1: % | DF1: di cui a breve termine | DG1: % | DH1: di cui a medio lungo termine | DI1: % | DJ1: Ratei e Risconti Passivi | DK1: % | DL1: Totale Passivo | DM1: %
I2: Valore | J2: % | K2: Nota | L2: Valore | M2: % | N2: Nota | O2: Valore | P2: % | Q2: Nota | R2: Valore | S2: % | T2: Nota | U2: Valore | V2: % | W2: Nota | X2: Valore | Y2: % | Z2: Nota | AA2: Valore | AB2: % | AC2: Nota | AD2: Valore | AE2: % | AF2: Nota | AG2: Valore | AH2: % | AI2: Nota | AJ2: Valore | AK2: % | AL2: Nota | AM2: Valore | AN2: % | AO2: Nota | AP2: Valore | AQ2: % | AR2: Nota | AS2: Valore | AT2: % | AU2: Nota | AV2: Valore | AW2: % | AX2: Nota | AY2: Valore | AZ2: % | BA2: Nota | BB2: Valore | BC2: % | BD2: Nota | BE2: Valore | BF2: % | BG2: Nota | BH2: Valore | BI2: % | BJ2: Nota

Sheet test
C3: Formazione Margini e Profitto 2023 dati in % del fatturato
C4: Fatturato | D4: =+calcoli!I3 -> 9038616
C5: Fatturato +/- Δ Rimanenze Prodotti | D5: =+calcoli!L3 -> 9038616
C6: Consumo di Materie Prime | D6: =+calcoli!O3 -> 6285561
C7: Margine Commerciale/Industriale Puro | D7: =+D5-D6 -> 2753055
C8: Altri ricavi | D8: =+calcoli!U3 -> 82030
C9: Margine Commerciale/Industriale Allargato | D9: =+D7+D8 -> 2835085
C10: Spese per Servizi | D10: =+calcoli!AA3 -> 1015920
C11: Costo del lavoro | D11: =+calcoli!AD3 -> 1052480
C12: +/- Altri Costi e Ricavi Operativi | D12: =+calcoli!AG3 -> 122827
C13: EBITDAR | D13: =+D9-D10-D11-D12 -> 643858
C14: Spese per affitti e noleggi | D14: =+calcoli!AM3 -> 25090
C15: EBITDA margin | D15: =+D13-D14 -> 618768
C16: Ammortamenti e Svalutazioni | D16: =+calcoli!AS3 -> 406552
C17: EBIT margin | D17: =+D15-D16 -> 212216
C18: Gestione finanziaria (interessi e rettifiche) | D18: =+calcoli!AY3 -> -44934
C19: Gestione straordinaria | D19: =+calcoli!BB3 -> 1031
C20: Imposte | D20: =+calcoli!BE3 -> 39284
C21: Profit margin | D21: =+D17+D18+D19-D20 -> 129029

Sheet ateco
B2: CLASSI
B3: CODICE | C3: DESCRIZIONE
B4: 01 | C4: Coltivazioni agricole e produzione di prodotti animali; caccia e servizi connessi
B5: 02 | C5: Silvicoltura ed utilizzo di aree forestali
B6: 03 | C6: Pesca e acquacoltura
B7: 05 | C7: Estrazione di carbone (esclusa torba)
B8: 06 | C8: Estrazione di petrolio greggio e di gas naturale
B9: 07 | C9: Estrazione di minerali metalliferi
B10: 08 | C10: Altre attivita di estrazione di minerali da cave e miniere
B11: 09 | C11: Attivita dei servizi di supporto all'estrazione
B12: 10 | C12: Industrie alimentari
B13: 11 | C13: Industria delle bevande
B14: 12 | C14: Industria del tabacco
... B93: 99 | C93: Organizzazioni ed organismi extraterritoriali
